[{"timestamp":1713657600000,"Open":"5.62300000","High":5.812,"Low":5.452,"Close":5.59,"Volume":1064353.2,"quote_asset_volume":"5986054.26810000","NumTrades":46478,"taker_buy_base_asset_volume":"521399.40000000","taker_buy_quote_asset_volume":"2936581.28350000"},{"timestamp":1713744000000,"Open":"5.58200000","High":5.999,"Low":5.579,"Close":5.765,"Volume":856020.8,"quote_asset_volume":"4902076.02790000","NumTrades":34674,"taker_buy_base_asset_volume":"409740.00000000","taker_buy_quote_asset_volume":"2346566.34060000"},{"timestamp":1713830400000,"Open":"5.76500000","High":5.87,"Low":5.602,"Close":5.635,"Volume":602691.0,"quote_asset_volume":"3440174.25620000","NumTrades":28836,"taker_buy_base_asset_volume":"268491.70000000","taker_buy_quote_asset_volume":"1533874.01650000"},{"timestamp":1713916800000,"Open":"5.63300000","High":5.911,"Low":5.294,"Close":5.366,"Volume":848860.0,"quote_asset_volume":"4710727.33650000","NumTrades":37152,"taker_buy_base_asset_volume":"415561.90000000","taker_buy_quote_asset_volume":"2306731.56290000"},{"timestamp":1714003200000,"Open":"5.36900000","High":5.537,"Low":5.172,"Close":5.428,"Volume":591939.2,"quote_asset_volume":"3155941.62780000","NumTrades":28125,"taker_buy_base_asset_volume":"286252.10000000","taker_buy_quote_asset_volume":"1525290.25980000"},{"timestamp":1714089600000,"Open":"5.43000000","High":5.535,"Low":5.278,"Close":5.468,"Volume":571758.4,"quote_asset_volume":"3094294.61130000","NumTrades":28067,"taker_buy_base_asset_volume":"265357.40000000","taker_buy_quote_asset_volume":"1435985.26250000"},{"timestamp":1714176000000,"Open":"5.47100000","High":5.58,"Low":5.192,"Close":5.435,"Volume":878891.0,"quote_asset_volume":"4788198.97860000","NumTrades":36365,"taker_buy_base_asset_volume":"448891.30000000","taker_buy_quote_asset_volume":"2449613.39090000"},{"timestamp":1714262400000,"Open":"5.43500000","High":5.663,"Low":5.423,"Close":5.48,"Volume":600040.5,"quote_asset_volume":"3325333.54720000","NumTrades":23878,"taker_buy_base_asset_volume":"265511.60000000","taker_buy_quote_asset_volume":"1470682.88460000"},{"timestamp":1714348800000,"Open":"5.47800000","High":5.631,"Low":5.298,"Close":5.521,"Volume":618620.5,"quote_asset_volume":"3361911.17710000","NumTrades":28444,"taker_buy_base_asset_volume":"296221.30000000","taker_buy_quote_asset_volume":"1609109.40870000"},{"timestamp":1714435200000,"Open":"5.51800000","High":5.579,"Low":4.846,"Close":4.992,"Volume":954676.1,"quote_asset_volume":"4905469.78500000","NumTrades":48252,"taker_buy_base_asset_volume":"498926.20000000","taker_buy_quote_asset_volume":"2549795.34590000"},{"timestamp":1714521600000,"Open":"4.98900000","High":5.003,"Low":4.548,"Close":4.862,"Volume":947059.1,"quote_asset_volume":"4481241.79810000","NumTrades":42167,"taker_buy_base_asset_volume":"476225.70000000","taker_buy_quote_asset_volume":"2251705.34450000"},{"timestamp":1714608000000,"Open":"4.85800000","High":4.97,"Low":4.668,"Close":4.893,"Volume":456899.5,"quote_asset_volume":"2203189.35590000","NumTrades":25211,"taker_buy_base_asset_volume":"200959.10000000","taker_buy_quote_asset_volume":"968609.37540000"},{"timestamp":1714694400000,"Open":"4.89300000","High":5.212,"Low":4.825,"Close":5.116,"Volume":571534.1,"quote_asset_volume":"2867349.50830000","NumTrades":33751,"taker_buy_base_asset_volume":"261631.50000000","taker_buy_quote_asset_volume":"1312405.82110000"},{"timestamp":1714780800000,"Open":"5.11700000","High":5.24,"Low":5.064,"Close":5.077,"Volume":512806.6,"quote_asset_volume":"2627341.39660000","NumTrades":24032,"taker_buy_base_asset_volume":"249410.00000000","taker_buy_quote_asset_volume":"1278236.85590000"},{"timestamp":1714867200000,"Open":"5.08000000","High":5.245,"Low":4.998,"Close":5.181,"Volume":736475.9,"quote_asset_volume":"3769831.02750000","NumTrades":31164,"taker_buy_base_asset_volume":"373923.60000000","taker_buy_quote_asset_volume":"1912951.24340000"},{"timestamp":1714953600000,"Open":"5.18100000","High":5.33,"Low":5.067,"Close":5.114,"Volume":470326.8,"quote_asset_volume":"2440455.12200000","NumTrades":22189,"taker_buy_base_asset_volume":"205870.00000000","taker_buy_quote_asset_volume":"1067509.88610000"},{"timestamp":1715040000000,"Open":"5.11500000","High":5.291,"Low":5.055,"Close":5.08,"Volume":668938.8,"quote_asset_volume":"3468765.77010000","NumTrades":31304,"taker_buy_base_asset_volume":"326930.50000000","taker_buy_quote_asset_volume":"1695606.81500000"},{"timestamp":1715126400000,"Open":"5.07800000","High":5.252,"Low":5.002,"Close":5.101,"Volume":792056.6,"quote_asset_volume":"4045262.06370000","NumTrades":27439,"taker_buy_base_asset_volume":"378169.00000000","taker_buy_quote_asset_volume":"1931042.02240000"},{"timestamp":1715212800000,"Open":"5.10200000","High":5.268,"Low":5.013,"Close":5.245,"Volume":466626.3,"quote_asset_volume":"2397473.42380000","NumTrades":19336,"taker_buy_base_asset_volume":"228152.50000000","taker_buy_quote_asset_volume":"1172513.20450000"},{"timestamp":1715299200000,"Open":"5.24500000","High":5.295,"Low":4.888,"Close":4.974,"Volume":584535.2,"quote_asset_volume":"2994707.50800000","NumTrades":27845,"taker_buy_base_asset_volume":"279065.50000000","taker_buy_quote_asset_volume":"1431376.78820000"},{"timestamp":1715385600000,"Open":"4.97300000","High":5.072,"Low":4.921,"Close":4.936,"Volume":213449.8,"quote_asset_volume":"1064305.27210000","NumTrades":10381,"taker_buy_base_asset_volume":"112884.70000000","taker_buy_quote_asset_volume":"562348.20100000"},{"timestamp":1715472000000,"Open":"4.92900000","High":4.994,"Low":4.862,"Close":4.902,"Volume":172818.5,"quote_asset_volume":"855021.97380000","NumTrades":8349,"taker_buy_base_asset_volume":"86488.80000000","taker_buy_quote_asset_volume":"427809.05960000"},{"timestamp":1715558400000,"Open":"4.90200000","High":4.995,"Low":4.699,"Close":4.9,"Volume":406431.7,"quote_asset_volume":"1981392.95280000","NumTrades":18758,"taker_buy_base_asset_volume":"207505.00000000","taker_buy_quote_asset_volume":"1012146.23770000"},{"timestamp":1715644800000,"Open":"4.90000000","High":4.949,"Low":4.769,"Close":4.783,"Volume":389943.6,"quote_asset_volume":"1892843.63780000","NumTrades":19811,"taker_buy_base_asset_volume":"191473.90000000","taker_buy_quote_asset_volume":"929428.92020000"},{"timestamp":1715731200000,"Open":"4.78400000","High":5.083,"Low":4.751,"Close":5.044,"Volume":406382.7,"quote_asset_volume":"1993608.07880000","NumTrades":15581,"taker_buy_base_asset_volume":"192963.10000000","taker_buy_quote_asset_volume":"948310.73630000"},{"timestamp":1715817600000,"Open":"5.04700000","High":5.095,"Low":4.931,"Close":5.038,"Volume":358578.5,"quote_asset_volume":"1807583.72160000","NumTrades":17167,"taker_buy_base_asset_volume":"182559.20000000","taker_buy_quote_asset_volume":"920571.33420000"},{"timestamp":1715904000000,"Open":"5.03800000","High":5.216,"Low":4.984,"Close":5.182,"Volume":342993.8,"quote_asset_volume":"1759835.41820000","NumTrades":14452,"taker_buy_base_asset_volume":"170234.80000000","taker_buy_quote_asset_volume":"872998.52280000"},{"timestamp":1715990400000,"Open":"5.18100000","High":5.224,"Low":5.113,"Close":5.167,"Volume":236321.5,"quote_asset_volume":"1224396.77250000","NumTrades":11250,"taker_buy_base_asset_volume":"120282.10000000","taker_buy_quote_asset_volume":"623212.87530000"},{"timestamp":1716076800000,"Open":"5.16700000","High":5.184,"Low":4.938,"Close":4.979,"Volume":265161.4,"quote_asset_volume":"1345712.45900000","NumTrades":11887,"taker_buy_base_asset_volume":"120305.20000000","taker_buy_quote_asset_volume":"611210.19800000"},{"timestamp":1716163200000,"Open":"4.98000000","High":5.376,"Low":4.91,"Close":5.366,"Volume":670765.3,"quote_asset_volume":"3486847.31990000","NumTrades":32994,"taker_buy_base_asset_volume":"354015.50000000","taker_buy_quote_asset_volume":"1841700.33460000"},{"timestamp":1716249600000,"Open":"5.36800000","High":5.398,"Low":5.234,"Close":5.292,"Volume":604134.2,"quote_asset_volume":"3214490.98850000","NumTrades":28370,"taker_buy_base_asset_volume":"277532.80000000","taker_buy_quote_asset_volume":"1477575.38190000"},{"timestamp":1716336000000,"Open":"5.29400000","High":5.303,"Low":5.118,"Close":5.191,"Volume":474401.7,"quote_asset_volume":"2480572.09510000","NumTrades":25332,"taker_buy_base_asset_volume":"243182.80000000","taker_buy_quote_asset_volume":"1271412.24770000"},{"timestamp":1716422400000,"Open":"5.19200000","High":5.25,"Low":4.793,"Close":5.004,"Volume":735754.1,"quote_asset_volume":"3695095.09950000","NumTrades":44044,"taker_buy_base_asset_volume":"361158.70000000","taker_buy_quote_asset_volume":"1812429.79310000"},{"timestamp":1716508800000,"Open":"5.00200000","High":5.138,"Low":4.89,"Close":5.138,"Volume":351010.6,"quote_asset_volume":"1764136.66250000","NumTrades":16611,"taker_buy_base_asset_volume":"172801.80000000","taker_buy_quote_asset_volume":"867801.68560000"},{"timestamp":1716595200000,"Open":"5.13600000","High":5.257,"Low":5.12,"Close":5.192,"Volume":439963.4,"quote_asset_volume":"2276731.79630000","NumTrades":17674,"taker_buy_base_asset_volume":"211986.20000000","taker_buy_quote_asset_volume":"1097631.57150000"},{"timestamp":1716681600000,"Open":"5.19500000","High":5.221,"Low":5.085,"Close":5.119,"Volume":408128.3,"quote_asset_volume":"2103211.56710000","NumTrades":18017,"taker_buy_base_asset_volume":"189941.90000000","taker_buy_quote_asset_volume":"979352.06730000"},{"timestamp":1716768000000,"Open":"5.12100000","High":5.308,"Low":5.073,"Close":5.229,"Volume":503004.1,"quote_asset_volume":"2610801.79530000","NumTrades":18028,"taker_buy_base_asset_volume":"246217.30000000","taker_buy_quote_asset_volume":"1279230.03630000"},{"timestamp":1716854400000,"Open":"5.23200000","High":5.337,"Low":5.089,"Close":5.236,"Volume":893924.5,"quote_asset_volume":"4656477.88690000","NumTrades":43753,"taker_buy_base_asset_volume":"422066.80000000","taker_buy_quote_asset_volume":"2198811.63110000"},{"timestamp":1716940800000,"Open":"5.23700000","High":5.307,"Low":5.106,"Close":5.128,"Volume":674934.6,"quote_asset_volume":"3512675.17860000","NumTrades":30255,"taker_buy_base_asset_volume":"307576.40000000","taker_buy_quote_asset_volume":"1600611.96120000"},{"timestamp":1717027200000,"Open":"5.12600000","High":5.152,"Low":4.911,"Close":4.99,"Volume":436268.4,"quote_asset_volume":"2192059.68410000","NumTrades":23663,"taker_buy_base_asset_volume":"198997.10000000","taker_buy_quote_asset_volume":"999619.29500000"},{"timestamp":1717113600000,"Open":"4.98800000","High":5.015,"Low":4.867,"Close":4.984,"Volume":282191.7,"quote_asset_volume":"1398371.94510000","NumTrades":17144,"taker_buy_base_asset_volume":"131277.60000000","taker_buy_quote_asset_volume":"651010.45960000"},{"timestamp":1717200000000,"Open":"4.98300000","High":4.99,"Low":4.942,"Close":4.962,"Volume":140688.9,"quote_asset_volume":"698243.40140000","NumTrades":8175,"taker_buy_base_asset_volume":"54884.30000000","taker_buy_quote_asset_volume":"272460.39400000"},{"timestamp":1717286400000,"Open":"4.96000000","High":4.997,"Low":4.832,"Close":4.902,"Volume":392412.4,"quote_asset_volume":"1932547.37010000","NumTrades":16407,"taker_buy_base_asset_volume":"155560.10000000","taker_buy_quote_asset_volume":"765587.02060000"},{"timestamp":1717372800000,"Open":"4.90500000","High":5.017,"Low":4.865,"Close":4.918,"Volume":518187.8,"quote_asset_volume":"2565173.44770000","NumTrades":22760,"taker_buy_base_asset_volume":"254534.70000000","taker_buy_quote_asset_volume":"1261177.99170000"},{"timestamp":1717459200000,"Open":"4.91700000","High":5.05,"Low":4.888,"Close":5.021,"Volume":648495.8,"quote_asset_volume":"3239598.50590000","NumTrades":27743,"taker_buy_base_asset_volume":"309165.60000000","taker_buy_quote_asset_volume":"1545529.80150000"},{"timestamp":1717545600000,"Open":"5.02400000","High":5.093,"Low":5.0,"Close":5.072,"Volume":546658.2,"quote_asset_volume":"2760652.23020000","NumTrades":20397,"taker_buy_base_asset_volume":"273201.30000000","taker_buy_quote_asset_volume":"1380135.75850000"},{"timestamp":1717632000000,"Open":"5.07200000","High":5.08,"Low":4.905,"Close":4.986,"Volume":306897.3,"quote_asset_volume":"1538125.77570000","NumTrades":12797,"taker_buy_base_asset_volume":"119298.90000000","taker_buy_quote_asset_volume":"598194.86110000"},{"timestamp":1717718400000,"Open":"4.98100000","High":5.057,"Low":4.096,"Close":4.574,"Volume":1148099.8999999999,"quote_asset_volume":"5324421.60590000","NumTrades":49974,"taker_buy_base_asset_volume":"568739.60000000","taker_buy_quote_asset_volume":"2624396.91620000"},{"timestamp":1717804800000,"Open":"4.57300000","High":4.59,"Low":4.287,"Close":4.335,"Volume":562177.7,"quote_asset_volume":"2482616.05370000","NumTrades":27484,"taker_buy_base_asset_volume":"322763.00000000","taker_buy_quote_asset_volume":"1426901.64070000"},{"timestamp":1717891200000,"Open":"4.33500000","High":4.481,"Low":4.263,"Close":4.427,"Volume":214989.2,"quote_asset_volume":"939210.70820000","NumTrades":11914,"taker_buy_base_asset_volume":"108658.90000000","taker_buy_quote_asset_volume":"474168.89830000"},{"timestamp":1717977600000,"Open":"4.42800000","High":4.434,"Low":4.311,"Close":4.347,"Volume":229579.2,"quote_asset_volume":"1004672.13520000","NumTrades":15315,"taker_buy_base_asset_volume":"112556.00000000","taker_buy_quote_asset_volume":"492489.15600000"},{"timestamp":1718064000000,"Open":"4.34800000","High":4.361,"Low":4.021,"Close":4.113,"Volume":442899.1,"quote_asset_volume":"1851889.94370000","NumTrades":23421,"taker_buy_base_asset_volume":"214409.90000000","taker_buy_quote_asset_volume":"895860.79620000"},{"timestamp":1718150400000,"Open":"4.11500000","High":4.417,"Low":4.041,"Close":4.324,"Volume":754613.6,"quote_asset_volume":"3237846.99080000","NumTrades":35668,"taker_buy_base_asset_volume":"419108.30000000","taker_buy_quote_asset_volume":"1796106.60960000"},{"timestamp":1718236800000,"Open":"4.32600000","High":4.425,"Low":4.114,"Close":4.142,"Volume":443315.6,"quote_asset_volume":"1891037.86140000","NumTrades":20687,"taker_buy_base_asset_volume":"236549.70000000","taker_buy_quote_asset_volume":"1009588.97940000"},{"timestamp":1718323200000,"Open":"4.14900000","High":4.211,"Low":3.85,"Close":4.026,"Volume":387367.6,"quote_asset_volume":"1573146.88860000","NumTrades":18379,"taker_buy_base_asset_volume":"181907.00000000","taker_buy_quote_asset_volume":"738571.77900000"},{"timestamp":1718409600000,"Open":"4.02800000","High":4.102,"Low":4.001,"Close":4.082,"Volume":143176.1,"quote_asset_volume":"582228.27650000","NumTrades":7634,"taker_buy_base_asset_volume":"65150.40000000","taker_buy_quote_asset_volume":"265027.87970000"},{"timestamp":1718496000000,"Open":"4.08400000","High":4.132,"Low":4.006,"Close":4.11,"Volume":176715.4,"quote_asset_volume":"721659.51040000","NumTrades":9093,"taker_buy_base_asset_volume":"87330.50000000","taker_buy_quote_asset_volume":"356855.65180000"},{"timestamp":1718582400000,"Open":"4.11000000","High":4.875,"Low":3.517,"Close":3.733,"Volume":1912698.8,"quote_asset_volume":"7366874.53690000","NumTrades":66054,"taker_buy_base_asset_volume":"972389.60000000","taker_buy_quote_asset_volume":"3736281.03550000"},{"timestamp":1718668800000,"Open":"3.73100000","High":3.744,"Low":3.167,"Close":3.52,"Volume":1160652.3999999999,"quote_asset_volume":"3975263.29570000","NumTrades":44411,"taker_buy_base_asset_volume":"578524.00000000","taker_buy_quote_asset_volume":"1980600.30990000"},{"timestamp":1718755200000,"Open":"3.52100000","High":3.675,"Low":3.47,"Close":3.604,"Volume":385773.1,"quote_asset_volume":"1382110.51070000","NumTrades":16350,"taker_buy_base_asset_volume":"188259.40000000","taker_buy_quote_asset_volume":"674489.28140000"},{"timestamp":1718841600000,"Open":"3.60300000","High":3.871,"Low":3.584,"Close":3.655,"Volume":514243.2,"quote_asset_volume":"1921946.30910000","NumTrades":20308,"taker_buy_base_asset_volume":"257605.30000000","taker_buy_quote_asset_volume":"963439.48970000"},{"timestamp":1718928000000,"Open":"3.65600000","High":4.267,"Low":3.605,"Close":4.127,"Volume":2659204.7999999998,"quote_asset_volume":"10522014.29090000","NumTrades":92542,"taker_buy_base_asset_volume":"1408437.10000000","taker_buy_quote_asset_volume":"5570746.70940000"}]