[{"timestamp":1713139200000,"Open":"21.85000000","High":22.73,"Low":20.7,"Close":21.53,"Volume":53225.485,"quote_asset_volume":"1164490.84570000","NumTrades":14264,"taker_buy_base_asset_volume":"28614.67700000","taker_buy_quote_asset_volume":"626924.06758000"},{"timestamp":1713225600000,"Open":"21.53000000","High":21.93,"Low":20.32,"Close":21.53,"Volume":36375.183,"quote_asset_volume":"774438.30346000","NumTrades":10298,"taker_buy_base_asset_volume":"17855.53400000","taker_buy_quote_asset_volume":"380842.72059000"},{"timestamp":1713312000000,"Open":"21.53000000","High":21.84,"Low":19.94,"Close":20.49,"Volume":50026.845,"quote_asset_volume":"1046254.94411000","NumTrades":15875,"taker_buy_base_asset_volume":"24162.71400000","taker_buy_quote_asset_volume":"505154.90340000"},{"timestamp":1713398400000,"Open":"20.48000000","High":21.97,"Low":20.09,"Close":21.48,"Volume":47484.052,"quote_asset_volume":"992671.82341000","NumTrades":22246,"taker_buy_base_asset_volume":"25285.06800000","taker_buy_quote_asset_volume":"529455.87772000"},{"timestamp":1713484800000,"Open":"21.48000000","High":23.5,"Low":20.18,"Close":22.32,"Volume":67337.802,"quote_asset_volume":"1478543.35572000","NumTrades":33275,"taker_buy_base_asset_volume":"37529.01300000","taker_buy_quote_asset_volume":"825396.00757000"},{"timestamp":1713571200000,"Open":"22.32000000","High":24.0,"Low":22.02,"Close":23.52,"Volume":107741.272,"quote_asset_volume":"2454331.96082000","NumTrades":52965,"taker_buy_base_asset_volume":"55269.79100000","taker_buy_quote_asset_volume":"1263374.88922000"},{"timestamp":1713657600000,"Open":"23.50000000","High":24.88,"Low":23.23,"Close":23.49,"Volume":89764.922,"quote_asset_volume":"2132620.96852000","NumTrades":46555,"taker_buy_base_asset_volume":"44418.82800000","taker_buy_quote_asset_volume":"1056780.69389000"},{"timestamp":1713744000000,"Open":"23.50000000","High":25.54,"Low":23.35,"Close":23.46,"Volume":180507.042,"quote_asset_volume":"4430232.43081000","NumTrades":58114,"taker_buy_base_asset_volume":"82968.25300000","taker_buy_quote_asset_volume":"2040365.40046000"},{"timestamp":1713830400000,"Open":"23.46000000","High":23.76,"Low":22.57,"Close":22.73,"Volume":54236.092,"quote_asset_volume":"1257683.25683000","NumTrades":15676,"taker_buy_base_asset_volume":"25763.93800000","taker_buy_quote_asset_volume":"597324.63565000"},{"timestamp":1713916800000,"Open":"22.74000000","High":23.18,"Low":21.39,"Close":21.72,"Volume":48705.897,"quote_asset_volume":"1090281.59147000","NumTrades":16360,"taker_buy_base_asset_volume":"24548.45700000","taker_buy_quote_asset_volume":"550476.07285000"},{"timestamp":1714003200000,"Open":"21.72000000","High":23.04,"Low":21.09,"Close":22.02,"Volume":35237.22,"quote_asset_volume":"768405.57493000","NumTrades":16377,"taker_buy_base_asset_volume":"16768.28600000","taker_buy_quote_asset_volume":"366592.93854000"},{"timestamp":1714089600000,"Open":"22.03000000","High":22.11,"Low":21.06,"Close":21.24,"Volume":27680.395,"quote_asset_volume":"594775.88297000","NumTrades":12198,"taker_buy_base_asset_volume":"12646.86800000","taker_buy_quote_asset_volume":"271840.14182000"}]