[{"timestamp":1721433600000,"Open":"14.81000000","High":15.58,"Low":14.57,"Close":15.45,"Volume":92052.48,"quote_asset_volume":"1379921.52490000","NumTrades":20530,"taker_buy_base_asset_volume":"39274.31000000","taker_buy_quote_asset_volume":"588310.59520000"},{"timestamp":1721520000000,"Open":"15.46000000","High":15.98,"Low":14.71,"Close":15.76,"Volume":155282.56,"quote_asset_volume":"2394695.46200000","NumTrades":29993,"taker_buy_base_asset_volume":"71131.26000000","taker_buy_quote_asset_volume":"1097482.71540000"},{"timestamp":1721606400000,"Open":"15.77000000","High":15.91,"Low":14.65,"Close":14.73,"Volume":76027.06,"quote_asset_volume":"1157740.35770000","NumTrades":16494,"taker_buy_base_asset_volume":"30668.07000000","taker_buy_quote_asset_volume":"465317.71200000"},{"timestamp":1721692800000,"Open":"14.74000000","High":15.2,"Low":13.95,"Close":14.13,"Volume":82547.04,"quote_asset_volume":"1207498.91560000","NumTrades":20128,"taker_buy_base_asset_volume":"42239.81000000","taker_buy_quote_asset_volume":"617739.52690000"},{"timestamp":1721779200000,"Open":"14.13000000","High":14.48,"Low":13.42,"Close":13.59,"Volume":75235.75,"quote_asset_volume":"1051677.32230000","NumTrades":15337,"taker_buy_base_asset_volume":"36264.84000000","taker_buy_quote_asset_volume":"506612.67550000"},{"timestamp":1721865600000,"Open":"13.60000000","High":13.67,"Low":12.66,"Close":13.3,"Volume":81347.38,"quote_asset_volume":"1070480.90550000","NumTrades":18510,"taker_buy_base_asset_volume":"40485.22000000","taker_buy_quote_asset_volume":"532452.36450000"},{"timestamp":1721952000000,"Open":"13.29000000","High":15.24,"Low":13.25,"Close":15.1,"Volume":129855.33,"quote_asset_volume":"1884093.84870000","NumTrades":25071,"taker_buy_base_asset_volume":"72274.89000000","taker_buy_quote_asset_volume":"1046083.35530000"},{"timestamp":1722038400000,"Open":"15.10000000","High":15.37,"Low":14.72,"Close":14.93,"Volume":69235.2,"quote_asset_volume":"1037911.08980000","NumTrades":15515,"taker_buy_base_asset_volume":"32644.66000000","taker_buy_quote_asset_volume":"489688.82650000"},{"timestamp":1722124800000,"Open":"14.93000000","High":15.06,"Low":14.27,"Close":14.44,"Volume":39282.63,"quote_asset_volume":"574277.97830000","NumTrades":9502,"taker_buy_base_asset_volume":"18466.05000000","taker_buy_quote_asset_volume":"270043.53160000"},{"timestamp":1722211200000,"Open":"14.44000000","High":16.68,"Low":14.42,"Close":14.8,"Volume":371524.41,"quote_asset_volume":"5745256.84520000","NumTrades":60331,"taker_buy_base_asset_volume":"178428.31000000","taker_buy_quote_asset_volume":"2769867.36560000"},{"timestamp":1722297600000,"Open":"14.80000000","High":14.94,"Low":13.79,"Close":14.0,"Volume":63317.33,"quote_asset_volume":"914635.88740000","NumTrades":15126,"taker_buy_base_asset_volume":"29786.32000000","taker_buy_quote_asset_volume":"430539.79380000"},{"timestamp":1722384000000,"Open":"14.00000000","High":14.51,"Low":13.72,"Close":13.76,"Volume":56364.8,"quote_asset_volume":"798335.27790000","NumTrades":13459,"taker_buy_base_asset_volume":"27693.17000000","taker_buy_quote_asset_volume":"392067.92140000"},{"timestamp":1722470400000,"Open":"13.75000000","High":14.07,"Low":12.33,"Close":13.4,"Volume":193564.78,"quote_asset_volume":"2542904.41140000","NumTrades":29013,"taker_buy_base_asset_volume":"111746.75000000","taker_buy_quote_asset_volume":"1464191.25290000"},{"timestamp":1722556800000,"Open":"13.41000000","High":13.57,"Low":12.4,"Close":12.67,"Volume":105956.67,"quote_asset_volume":"1374941.22160000","NumTrades":21717,"taker_buy_base_asset_volume":"50176.65000000","taker_buy_quote_asset_volume":"651380.58460000"},{"timestamp":1722643200000,"Open":"12.67000000","High":12.74,"Low":11.47,"Close":11.77,"Volume":87471.98,"quote_asset_volume":"1057815.31540000","NumTrades":19255,"taker_buy_base_asset_volume":"45254.43000000","taker_buy_quote_asset_volume":"548661.18200000"},{"timestamp":1722729600000,"Open":"11.78000000","High":12.15,"Low":10.91,"Close":11.24,"Volume":115097.24,"quote_asset_volume":"1334334.19620000","NumTrades":23998,"taker_buy_base_asset_volume":"57039.55000000","taker_buy_quote_asset_volume":"662061.49390000"},{"timestamp":1722816000000,"Open":"11.24000000","High":11.6,"Low":9.31,"Close":11.08,"Volume":326730.49,"quote_asset_volume":"3414554.99470000","NumTrades":70091,"taker_buy_base_asset_volume":"152032.58000000","taker_buy_quote_asset_volume":"1589047.45500000"},{"timestamp":1722902400000,"Open":"11.09000000","High":11.81,"Low":11.07,"Close":11.56,"Volume":141398.4,"quote_asset_volume":"1627335.01510000","NumTrades":26225,"taker_buy_base_asset_volume":"70667.57000000","taker_buy_quote_asset_volume":"813712.13430000"},{"timestamp":1722988800000,"Open":"11.55000000","High":11.97,"Low":11.01,"Close":11.18,"Volume":73995.15,"quote_asset_volume":"853592.50860000","NumTrades":19014,"taker_buy_base_asset_volume":"34221.45000000","taker_buy_quote_asset_volume":"394600.77090000"},{"timestamp":1723075200000,"Open":"11.18000000","High":12.66,"Low":10.95,"Close":12.61,"Volume":124569.07,"quote_asset_volume":"1499443.07340000","NumTrades":17536,"taker_buy_base_asset_volume":"66714.74000000","taker_buy_quote_asset_volume":"803791.48570000"},{"timestamp":1723161600000,"Open":"12.63000000","High":12.63,"Low":11.93,"Close":12.21,"Volume":60020.19,"quote_asset_volume":"732619.21530000","NumTrades":12536,"taker_buy_base_asset_volume":"30739.03000000","taker_buy_quote_asset_volume":"375188.47760000"},{"timestamp":1723248000000,"Open":"12.21000000","High":12.43,"Low":12.09,"Close":12.36,"Volume":32969.27,"quote_asset_volume":"404963.06950000","NumTrades":6212,"taker_buy_base_asset_volume":"14201.97000000","taker_buy_quote_asset_volume":"174517.91630000"},{"timestamp":1723334400000,"Open":"12.34000000","High":12.63,"Low":11.3,"Close":11.42,"Volume":63121.23,"quote_asset_volume":"761818.84150000","NumTrades":15178,"taker_buy_base_asset_volume":"27375.48000000","taker_buy_quote_asset_volume":"330266.14380000"},{"timestamp":1723420800000,"Open":"11.41000000","High":12.24,"Low":11.41,"Close":12.03,"Volume":89265.09,"quote_asset_volume":"1064813.09980000","NumTrades":14788,"taker_buy_base_asset_volume":"42680.85000000","taker_buy_quote_asset_volume":"508917.30270000"},{"timestamp":1723507200000,"Open":"12.03000000","High":12.3,"Low":11.69,"Close":12.08,"Volume":59973.22,"quote_asset_volume":"717822.22970000","NumTrades":10865,"taker_buy_base_asset_volume":"28963.04000000","taker_buy_quote_asset_volume":"346808.80420000"},{"timestamp":1723593600000,"Open":"12.06000000","High":12.28,"Low":11.64,"Close":11.87,"Volume":44212.63,"quote_asset_volume":"530166.84350000","NumTrades":6977,"taker_buy_base_asset_volume":"21039.68000000","taker_buy_quote_asset_volume":"252462.31380000"},{"timestamp":1723680000000,"Open":"11.87000000","High":12.02,"Low":11.18,"Close":11.32,"Volume":41450.78,"quote_asset_volume":"481960.68350000","NumTrades":7623,"taker_buy_base_asset_volume":"20367.39000000","taker_buy_quote_asset_volume":"236802.05680000"},{"timestamp":1723766400000,"Open":"11.31000000","High":11.65,"Low":11.02,"Close":11.36,"Volume":58366.95,"quote_asset_volume":"662265.10560000","NumTrades":8788,"taker_buy_base_asset_volume":"30791.17000000","taker_buy_quote_asset_volume":"349529.58810000"},{"timestamp":1723852800000,"Open":"11.37000000","High":11.76,"Low":11.18,"Close":11.76,"Volume":40935.4,"quote_asset_volume":"468098.12110000","NumTrades":6116,"taker_buy_base_asset_volume":"22388.94000000","taker_buy_quote_asset_volume":"256002.29370000"},{"timestamp":1723939200000,"Open":"11.75000000","High":12.51,"Low":11.59,"Close":12.08,"Volume":58569.81,"quote_asset_volume":"709267.81110000","NumTrades":9379,"taker_buy_base_asset_volume":"27274.07000000","taker_buy_quote_asset_volume":"329812.91270000"},{"timestamp":1724025600000,"Open":"12.08000000","High":18.5,"Low":11.78,"Close":15.69,"Volume":1402255.1000000001,"quote_asset_volume":"20951015.85160000","NumTrades":184823,"taker_buy_base_asset_volume":"716713.31000000","taker_buy_quote_asset_volume":"10683423.06620000"},{"timestamp":1724112000000,"Open":"15.67000000","High":17.47,"Low":14.32,"Close":15.11,"Volume":1066790.3200000001,"quote_asset_volume":"16796908.72440000","NumTrades":129801,"taker_buy_base_asset_volume":"518517.32000000","taker_buy_quote_asset_volume":"8169345.93410000"},{"timestamp":1724198400000,"Open":"15.11000000","High":17.93,"Low":14.87,"Close":17.18,"Volume":744521.08,"quote_asset_volume":"12272523.62870000","NumTrades":77242,"taker_buy_base_asset_volume":"385940.25000000","taker_buy_quote_asset_volume":"6346115.06440000"},{"timestamp":1724284800000,"Open":"17.18000000","High":18.21,"Low":16.76,"Close":17.7,"Volume":365906.12,"quote_asset_volume":"6335085.66410000","NumTrades":45594,"taker_buy_base_asset_volume":"182332.81000000","taker_buy_quote_asset_volume":"3157430.74750000"},{"timestamp":1724371200000,"Open":"17.72000000","High":20.58,"Low":16.63,"Close":18.87,"Volume":464795.85,"quote_asset_volume":"8442260.87870000","NumTrades":63716,"taker_buy_base_asset_volume":"238991.94000000","taker_buy_quote_asset_volume":"4330200.16550000"},{"timestamp":1724457600000,"Open":"18.86000000","High":19.55,"Low":18.13,"Close":18.52,"Volume":216787.1,"quote_asset_volume":"4075226.48780000","NumTrades":37283,"taker_buy_base_asset_volume":"104475.02000000","taker_buy_quote_asset_volume":"1964855.24680000"},{"timestamp":1724544000000,"Open":"18.52000000","High":18.53,"Low":17.42,"Close":17.49,"Volume":93443.3,"quote_asset_volume":"1665412.50350000","NumTrades":15102,"taker_buy_base_asset_volume":"42554.03000000","taker_buy_quote_asset_volume":"758797.06770000"},{"timestamp":1724630400000,"Open":"17.49000000","High":17.66,"Low":16.37,"Close":16.47,"Volume":95624.85,"quote_asset_volume":"1633353.26810000","NumTrades":15900,"taker_buy_base_asset_volume":"39475.32000000","taker_buy_quote_asset_volume":"674030.21030000"},{"timestamp":1724716800000,"Open":"16.45000000","High":17.24,"Low":15.08,"Close":15.56,"Volume":100955.26,"quote_asset_volume":"1646557.84640000","NumTrades":17657,"taker_buy_base_asset_volume":"50948.61000000","taker_buy_quote_asset_volume":"833627.23020000"},{"timestamp":1724803200000,"Open":"15.55000000","High":16.01,"Low":14.89,"Close":15.32,"Volume":94741.97,"quote_asset_volume":"1466348.58310000","NumTrades":13958,"taker_buy_base_asset_volume":"45458.84000000","taker_buy_quote_asset_volume":"703870.40510000"},{"timestamp":1724889600000,"Open":"15.31000000","High":16.3,"Low":14.96,"Close":15.47,"Volume":74899.9,"quote_asset_volume":"1179821.02410000","NumTrades":12202,"taker_buy_base_asset_volume":"40412.67000000","taker_buy_quote_asset_volume":"638228.88680000"},{"timestamp":1724976000000,"Open":"15.45000000","High":15.49,"Low":14.76,"Close":15.26,"Volume":62161.64,"quote_asset_volume":"943290.70400000","NumTrades":10757,"taker_buy_base_asset_volume":"23440.38000000","taker_buy_quote_asset_volume":"356975.22320000"},{"timestamp":1725062400000,"Open":"15.28000000","High":15.37,"Low":14.62,"Close":14.75,"Volume":33724.0,"quote_asset_volume":"504361.16320000","NumTrades":8263,"taker_buy_base_asset_volume":"16793.42000000","taker_buy_quote_asset_volume":"251497.92290000"},{"timestamp":1725148800000,"Open":"14.73000000","High":14.79,"Low":13.42,"Close":13.54,"Volume":69647.56,"quote_asset_volume":"982862.13790000","NumTrades":15426,"taker_buy_base_asset_volume":"30723.73000000","taker_buy_quote_asset_volume":"434110.50820000"},{"timestamp":1725235200000,"Open":"13.53000000","High":14.49,"Low":13.49,"Close":14.29,"Volume":72764.91,"quote_asset_volume":"1017038.86450000","NumTrades":12196,"taker_buy_base_asset_volume":"37278.17000000","taker_buy_quote_asset_volume":"521893.25460000"},{"timestamp":1725321600000,"Open":"14.29000000","High":14.35,"Low":13.49,"Close":13.59,"Volume":48164.35,"quote_asset_volume":"672615.73310000","NumTrades":9805,"taker_buy_base_asset_volume":"21932.46000000","taker_buy_quote_asset_volume":"306275.40570000"},{"timestamp":1725408000000,"Open":"13.60000000","High":14.25,"Low":12.89,"Close":13.77,"Volume":89243.94,"quote_asset_volume":"1223447.17950000","NumTrades":12880,"taker_buy_base_asset_volume":"41791.52000000","taker_buy_quote_asset_volume":"571099.56980000"},{"timestamp":1725494400000,"Open":"13.77000000","High":13.92,"Low":13.24,"Close":13.29,"Volume":39227.71,"quote_asset_volume":"532621.25390000","NumTrades":8466,"taker_buy_base_asset_volume":"18991.29000000","taker_buy_quote_asset_volume":"258129.69360000"},{"timestamp":1725580800000,"Open":"13.29000000","High":13.58,"Low":12.29,"Close":12.69,"Volume":63285.86,"quote_asset_volume":"823344.69840000","NumTrades":12671,"taker_buy_base_asset_volume":"29642.24000000","taker_buy_quote_asset_volume":"385367.21960000"},{"timestamp":1725667200000,"Open":"12.69000000","High":13.29,"Low":12.56,"Close":12.97,"Volume":40057.16,"quote_asset_volume":"519743.83480000","NumTrades":9328,"taker_buy_base_asset_volume":"21721.09000000","taker_buy_quote_asset_volume":"281524.49010000"},{"timestamp":1725753600000,"Open":"12.97000000","High":13.46,"Low":12.9,"Close":13.24,"Volume":42621.5,"quote_asset_volume":"562990.23610000","NumTrades":7634,"taker_buy_base_asset_volume":"20004.15000000","taker_buy_quote_asset_volume":"264831.32680000"},{"timestamp":1725840000000,"Open":"13.26000000","High":14.57,"Low":13.22,"Close":14.28,"Volume":83705.38,"quote_asset_volume":"1167885.42290000","NumTrades":13099,"taker_buy_base_asset_volume":"49149.89000000","taker_buy_quote_asset_volume":"687442.93130000"},{"timestamp":1725926400000,"Open":"14.30000000","High":14.7,"Low":14.14,"Close":14.29,"Volume":95631.17,"quote_asset_volume":"1377561.68750000","NumTrades":14673,"taker_buy_base_asset_volume":"47047.22000000","taker_buy_quote_asset_volume":"678160.05940000"},{"timestamp":1726012800000,"Open":"14.30000000","High":14.33,"Low":13.75,"Close":14.24,"Volume":52453.16,"quote_asset_volume":"738534.30780000","NumTrades":8980,"taker_buy_base_asset_volume":"24944.51000000","taker_buy_quote_asset_volume":"351489.28330000"},{"timestamp":1726099200000,"Open":"14.24000000","High":15.05,"Low":14.1,"Close":14.89,"Volume":96606.24,"quote_asset_volume":"1411324.24650000","NumTrades":14127,"taker_buy_base_asset_volume":"51859.65000000","taker_buy_quote_asset_volume":"757086.41030000"},{"timestamp":1726185600000,"Open":"14.90000000","High":15.3,"Low":14.64,"Close":14.91,"Volume":100389.35,"quote_asset_volume":"1499682.31280000","NumTrades":12900,"taker_buy_base_asset_volume":"45957.91000000","taker_buy_quote_asset_volume":"686644.67960000"},{"timestamp":1726272000000,"Open":"14.89000000","High":14.92,"Low":14.59,"Close":14.69,"Volume":43789.24,"quote_asset_volume":"646012.15570000","NumTrades":5521,"taker_buy_base_asset_volume":"18285.04000000","taker_buy_quote_asset_volume":"269680.94450000"},{"timestamp":1726358400000,"Open":"14.69000000","High":14.82,"Low":13.53,"Close":13.68,"Volume":83558.28,"quote_asset_volume":"1189492.93610000","NumTrades":9602,"taker_buy_base_asset_volume":"39521.20000000","taker_buy_quote_asset_volume":"562126.30270000"},{"timestamp":1726444800000,"Open":"13.68000000","High":13.81,"Low":13.11,"Close":13.25,"Volume":50722.88,"quote_asset_volume":"682367.05620000","NumTrades":9663,"taker_buy_base_asset_volume":"21759.01000000","taker_buy_quote_asset_volume":"292914.56980000"},{"timestamp":1726531200000,"Open":"13.24000000","High":13.72,"Low":13.13,"Close":13.56,"Volume":17532.78,"quote_asset_volume":"236859.85070000","NumTrades":3524,"taker_buy_base_asset_volume":"8102.74000000","taker_buy_quote_asset_volume":"109514.89710000"}]