[{"timestamp":1701820800000,"Open":"4.74100000","High":5.3,"Low":4.679,"Close":4.891,"Volume":1245692.3,"quote_asset_volume":"6137226.58640000","NumTrades":53278,"taker_buy_base_asset_volume":"670077.00000000","taker_buy_quote_asset_volume":"3307031.17430000"},{"timestamp":1701907200000,"Open":"4.89000000","High":5.23,"Low":4.727,"Close":4.826,"Volume":1435229.5,"quote_asset_volume":"7046017.00420000","NumTrades":55452,"taker_buy_base_asset_volume":"676976.60000000","taker_buy_quote_asset_volume":"3336735.76410000"},{"timestamp":1701993600000,"Open":"4.82600000","High":5.047,"Low":4.769,"Close":4.948,"Volume":615873.3,"quote_asset_volume":"3008232.75180000","NumTrades":28800,"taker_buy_base_asset_volume":"299764.10000000","taker_buy_quote_asset_volume":"1466607.35530000"},{"timestamp":1702080000000,"Open":"4.94800000","High":6.728,"Low":4.875,"Close":6.105,"Volume":4424648.0,"quote_asset_volume":"26423780.83690000","NumTrades":163634,"taker_buy_base_asset_volume":"2328234.90000000","taker_buy_quote_asset_volume":"13896190.07660000"},{"timestamp":1702166400000,"Open":"6.10000000","High":6.828,"Low":5.334,"Close":5.566,"Volume":4759063.0999999996,"quote_asset_volume":"28480290.29500000","NumTrades":234086,"taker_buy_base_asset_volume":"2308271.70000000","taker_buy_quote_asset_volume":"13857597.94770000"},{"timestamp":1702252800000,"Open":"5.56200000","High":5.567,"Low":4.82,"Close":5.024,"Volume":1274920.8999999999,"quote_asset_volume":"6629600.89920000","NumTrades":58717,"taker_buy_base_asset_volume":"553605.00000000","taker_buy_quote_asset_volume":"2876874.26660000"},{"timestamp":1702339200000,"Open":"5.02400000","High":5.34,"Low":4.9,"Close":5.078,"Volume":917488.4,"quote_asset_volume":"4659366.62030000","NumTrades":41849,"taker_buy_base_asset_volume":"423260.10000000","taker_buy_quote_asset_volume":"2151697.94680000"},{"timestamp":1702425600000,"Open":"5.08000000","High":5.16,"Low":4.827,"Close":4.968,"Volume":612462.7,"quote_asset_volume":"3033564.65990000","NumTrades":26621,"taker_buy_base_asset_volume":"293963.00000000","taker_buy_quote_asset_volume":"1456340.51850000"},{"timestamp":1702512000000,"Open":"4.97000000","High":5.15,"Low":4.895,"Close":4.985,"Volume":494123.1,"quote_asset_volume":"2481020.15610000","NumTrades":24129,"taker_buy_base_asset_volume":"237954.00000000","taker_buy_quote_asset_volume":"1195315.02730000"},{"timestamp":1702598400000,"Open":"4.98500000","High":5.22,"Low":4.855,"Close":4.904,"Volume":668155.3,"quote_asset_volume":"3333062.41850000","NumTrades":33363,"taker_buy_base_asset_volume":"312809.60000000","taker_buy_quote_asset_volume":"1563506.34570000"},{"timestamp":1702684800000,"Open":"4.90500000","High":5.164,"Low":4.891,"Close":4.967,"Volume":546661.4,"quote_asset_volume":"2736322.35830000","NumTrades":28494,"taker_buy_base_asset_volume":"255878.60000000","taker_buy_quote_asset_volume":"1282306.27780000"},{"timestamp":1702771200000,"Open":"4.96300000","High":5.014,"Low":4.741,"Close":4.782,"Volume":476486.1,"quote_asset_volume":"2310846.17270000","NumTrades":24842,"taker_buy_base_asset_volume":"215260.10000000","taker_buy_quote_asset_volume":"1044231.11690000"},{"timestamp":1702857600000,"Open":"4.78300000","High":4.822,"Low":4.501,"Close":4.743,"Volume":380749.3,"quote_asset_volume":"1775653.26040000","NumTrades":24563,"taker_buy_base_asset_volume":"178364.30000000","taker_buy_quote_asset_volume":"832661.58180000"},{"timestamp":1702944000000,"Open":"4.74200000","High":4.81,"Low":4.597,"Close":4.655,"Volume":272991.7,"quote_asset_volume":"1284755.41340000","NumTrades":19414,"taker_buy_base_asset_volume":"134130.40000000","taker_buy_quote_asset_volume":"631385.73610000"},{"timestamp":1703030400000,"Open":"4.65700000","High":5.173,"Low":4.65,"Close":4.794,"Volume":1305762.6000000001,"quote_asset_volume":"6402256.96970000","NumTrades":64541,"taker_buy_base_asset_volume":"648140.50000000","taker_buy_quote_asset_volume":"3181407.88570000"},{"timestamp":1703116800000,"Open":"4.79200000","High":4.999,"Low":4.732,"Close":4.811,"Volume":397714.6,"quote_asset_volume":"1917268.32040000","NumTrades":22129,"taker_buy_base_asset_volume":"185500.30000000","taker_buy_quote_asset_volume":"895434.37900000"},{"timestamp":1703203200000,"Open":"4.81300000","High":4.903,"Low":4.751,"Close":4.88,"Volume":338877.8,"quote_asset_volume":"1636959.44520000","NumTrades":20263,"taker_buy_base_asset_volume":"168042.30000000","taker_buy_quote_asset_volume":"812521.93080000"},{"timestamp":1703289600000,"Open":"4.88300000","High":4.899,"Low":4.78,"Close":4.847,"Volume":300152.5,"quote_asset_volume":"1446023.55330000","NumTrades":15089,"taker_buy_base_asset_volume":"146061.80000000","taker_buy_quote_asset_volume":"704235.22550000"},{"timestamp":1703376000000,"Open":"4.85000000","High":5.295,"Low":4.82,"Close":5.184,"Volume":893061.7,"quote_asset_volume":"4486276.67990000","NumTrades":43893,"taker_buy_base_asset_volume":"463884.70000000","taker_buy_quote_asset_volume":"2334968.59330000"},{"timestamp":1703462400000,"Open":"5.18900000","High":5.26,"Low":4.905,"Close":5.095,"Volume":894358.2,"quote_asset_volume":"4536326.43220000","NumTrades":46643,"taker_buy_base_asset_volume":"427659.80000000","taker_buy_quote_asset_volume":"2171872.21960000"},{"timestamp":1703548800000,"Open":"5.09200000","High":5.163,"Low":4.891,"Close":4.987,"Volume":668619.9,"quote_asset_volume":"3344267.82130000","NumTrades":32813,"taker_buy_base_asset_volume":"309524.40000000","taker_buy_quote_asset_volume":"1550042.58850000"},{"timestamp":1703635200000,"Open":"4.99200000","High":5.076,"Low":4.901,"Close":5.031,"Volume":384727.3,"quote_asset_volume":"1917400.54470000","NumTrades":19569,"taker_buy_base_asset_volume":"179581.00000000","taker_buy_quote_asset_volume":"895768.34140000"},{"timestamp":1703721600000,"Open":"5.03200000","High":5.087,"Low":4.851,"Close":4.895,"Volume":324871.6,"quote_asset_volume":"1602824.97110000","NumTrades":17641,"taker_buy_base_asset_volume":"140457.60000000","taker_buy_quote_asset_volume":"693396.66420000"},{"timestamp":1703808000000,"Open":"4.90000000","High":5.1,"Low":4.79,"Close":4.917,"Volume":388109.6,"quote_asset_volume":"1914538.61860000","NumTrades":22751,"taker_buy_base_asset_volume":"189526.40000000","taker_buy_quote_asset_volume":"937053.04780000"},{"timestamp":1703894400000,"Open":"4.91700000","High":4.962,"Low":4.803,"Close":4.854,"Volume":189600.5,"quote_asset_volume":"924531.95710000","NumTrades":12160,"taker_buy_base_asset_volume":"87821.70000000","taker_buy_quote_asset_volume":"428654.24100000"},{"timestamp":1703980800000,"Open":"4.85300000","High":4.894,"Low":4.634,"Close":4.679,"Volume":246482.3,"quote_asset_volume":"1184607.40930000","NumTrades":13333,"taker_buy_base_asset_volume":"96406.60000000","taker_buy_quote_asset_volume":"464311.32570000"},{"timestamp":1704067200000,"Open":"4.67900000","High":4.891,"Low":4.632,"Close":4.863,"Volume":249704.9,"quote_asset_volume":"1187512.89760000","NumTrades":17821,"taker_buy_base_asset_volume":"131518.10000000","taker_buy_quote_asset_volume":"625921.44920000"},{"timestamp":1704153600000,"Open":"4.86400000","High":4.904,"Low":4.76,"Close":4.823,"Volume":377043.8,"quote_asset_volume":"1823822.81150000","NumTrades":19171,"taker_buy_base_asset_volume":"177978.50000000","taker_buy_quote_asset_volume":"861761.68140000"},{"timestamp":1704240000000,"Open":"4.82400000","High":4.952,"Low":4.208,"Close":4.426,"Volume":714825.8,"quote_asset_volume":"3236532.25290000","NumTrades":31222,"taker_buy_base_asset_volume":"325504.00000000","taker_buy_quote_asset_volume":"1472688.05920000"},{"timestamp":1704326400000,"Open":"4.42700000","High":4.645,"Low":4.36,"Close":4.556,"Volume":299194.5,"quote_asset_volume":"1356711.55470000","NumTrades":17185,"taker_buy_base_asset_volume":"140050.20000000","taker_buy_quote_asset_volume":"634906.99960000"},{"timestamp":1704412800000,"Open":"4.55900000","High":5.39,"Low":4.416,"Close":4.68,"Volume":2643463.1000000001,"quote_asset_volume":"13006754.73200000","NumTrades":116704,"taker_buy_base_asset_volume":"1315093.40000000","taker_buy_quote_asset_volume":"6481958.19240000"},{"timestamp":1704499200000,"Open":"4.67900000","High":4.996,"Low":4.549,"Close":4.603,"Volume":1400997.1000000001,"quote_asset_volume":"6649527.43890000","NumTrades":70674,"taker_buy_base_asset_volume":"682606.90000000","taker_buy_quote_asset_volume":"3246037.12340000"},{"timestamp":1704585600000,"Open":"4.60500000","High":4.728,"Low":4.496,"Close":4.525,"Volume":486645.7,"quote_asset_volume":"2244969.41930000","NumTrades":25231,"taker_buy_base_asset_volume":"236814.80000000","taker_buy_quote_asset_volume":"1094140.28330000"},{"timestamp":1704672000000,"Open":"4.52500000","High":4.65,"Low":4.304,"Close":4.556,"Volume":372424.7,"quote_asset_volume":"1669540.85560000","NumTrades":19645,"taker_buy_base_asset_volume":"179938.10000000","taker_buy_quote_asset_volume":"807987.43890000"},{"timestamp":1704758400000,"Open":"4.55700000","High":4.662,"Low":4.296,"Close":4.425,"Volume":398491.4,"quote_asset_volume":"1777539.66570000","NumTrades":20338,"taker_buy_base_asset_volume":"186339.30000000","taker_buy_quote_asset_volume":"831974.46520000"},{"timestamp":1704844800000,"Open":"4.43000000","High":4.675,"Low":4.347,"Close":4.612,"Volume":310663.7,"quote_asset_volume":"1390237.89960000","NumTrades":16439,"taker_buy_base_asset_volume":"146323.30000000","taker_buy_quote_asset_volume":"655415.20490000"},{"timestamp":1704931200000,"Open":"4.61400000","High":4.74,"Low":4.524,"Close":4.701,"Volume":402665.4,"quote_asset_volume":"1868920.68710000","NumTrades":18973,"taker_buy_base_asset_volume":"206516.40000000","taker_buy_quote_asset_volume":"959305.72910000"},{"timestamp":1705017600000,"Open":"4.70100000","High":4.875,"Low":4.487,"Close":4.534,"Volume":637874.9,"quote_asset_volume":"2979368.64830000","NumTrades":31626,"taker_buy_base_asset_volume":"308903.20000000","taker_buy_quote_asset_volume":"1445703.01520000"},{"timestamp":1705104000000,"Open":"4.53600000","High":5.038,"Low":4.516,"Close":4.712,"Volume":1274957.3999999999,"quote_asset_volume":"6135365.78810000","NumTrades":61252,"taker_buy_base_asset_volume":"662512.70000000","taker_buy_quote_asset_volume":"3191497.31730000"},{"timestamp":1705190400000,"Open":"4.71600000","High":4.89,"Low":4.555,"Close":4.677,"Volume":648659.5,"quote_asset_volume":"3078165.62110000","NumTrades":34295,"taker_buy_base_asset_volume":"305588.00000000","taker_buy_quote_asset_volume":"1452694.96010000"},{"timestamp":1705276800000,"Open":"4.67600000","High":4.832,"Low":4.62,"Close":4.673,"Volume":305249.7,"quote_asset_volume":"1434953.70350000","NumTrades":19201,"taker_buy_base_asset_volume":"143827.20000000","taker_buy_quote_asset_volume":"676602.01160000"},{"timestamp":1705363200000,"Open":"4.67100000","High":5.41,"Low":4.664,"Close":5.09,"Volume":2284296.3999999999,"quote_asset_volume":"11674479.71600000","NumTrades":106866,"taker_buy_base_asset_volume":"1146003.60000000","taker_buy_quote_asset_volume":"5858853.17320000"},{"timestamp":1705449600000,"Open":"5.08800000","High":5.82,"Low":4.955,"Close":5.001,"Volume":2578276.2000000002,"quote_asset_volume":"13753982.90100000","NumTrades":145204,"taker_buy_base_asset_volume":"1262770.80000000","taker_buy_quote_asset_volume":"6757386.27320000"},{"timestamp":1705536000000,"Open":"5.00200000","High":5.494,"Low":4.839,"Close":5.21,"Volume":1860823.3999999999,"quote_asset_volume":"9647200.95240000","NumTrades":117813,"taker_buy_base_asset_volume":"926653.70000000","taker_buy_quote_asset_volume":"4815033.98430000"},{"timestamp":1705622400000,"Open":"5.21200000","High":5.395,"Low":4.66,"Close":4.786,"Volume":1148597.3,"quote_asset_volume":"5699875.80950000","NumTrades":63857,"taker_buy_base_asset_volume":"528227.40000000","taker_buy_quote_asset_volume":"2622473.38330000"},{"timestamp":1705708800000,"Open":"4.78500000","High":5.18,"Low":4.705,"Close":4.963,"Volume":696812.7,"quote_asset_volume":"3427583.68960000","NumTrades":40520,"taker_buy_base_asset_volume":"332158.60000000","taker_buy_quote_asset_volume":"1634138.42950000"},{"timestamp":1705795200000,"Open":"4.96500000","High":5.142,"Low":4.812,"Close":4.826,"Volume":411767.2,"quote_asset_volume":"2032143.33610000","NumTrades":24054,"taker_buy_base_asset_volume":"195251.00000000","taker_buy_quote_asset_volume":"963884.65260000"},{"timestamp":1705881600000,"Open":"4.82700000","High":4.898,"Low":4.615,"Close":4.671,"Volume":517999.3,"quote_asset_volume":"2459730.33130000","NumTrades":32111,"taker_buy_base_asset_volume":"239248.10000000","taker_buy_quote_asset_volume":"1137104.21380000"},{"timestamp":1705968000000,"Open":"4.67100000","High":4.848,"Low":4.42,"Close":4.609,"Volume":672948.6,"quote_asset_volume":"3084083.13880000","NumTrades":38489,"taker_buy_base_asset_volume":"320760.50000000","taker_buy_quote_asset_volume":"1470883.45540000"},{"timestamp":1706054400000,"Open":"4.60800000","High":4.614,"Low":4.505,"Close":4.576,"Volume":255109.6,"quote_asset_volume":"1160859.45580000","NumTrades":14576,"taker_buy_base_asset_volume":"125567.20000000","taker_buy_quote_asset_volume":"571523.12260000"},{"timestamp":1706140800000,"Open":"4.57700000","High":4.598,"Low":4.433,"Close":4.53,"Volume":320099.1,"quote_asset_volume":"1445283.06070000","NumTrades":18644,"taker_buy_base_asset_volume":"154113.80000000","taker_buy_quote_asset_volume":"695949.81350000"},{"timestamp":1706227200000,"Open":"4.52800000","High":4.786,"Low":4.528,"Close":4.679,"Volume":491589.1,"quote_asset_volume":"2297042.05110000","NumTrades":28797,"taker_buy_base_asset_volume":"234742.90000000","taker_buy_quote_asset_volume":"1097292.56040000"},{"timestamp":1706313600000,"Open":"4.68200000","High":4.731,"Low":4.629,"Close":4.666,"Volume":212022.8,"quote_asset_volume":"992480.45040000","NumTrades":9630,"taker_buy_base_asset_volume":"99611.90000000","taker_buy_quote_asset_volume":"466570.62540000"},{"timestamp":1706400000000,"Open":"4.66900000","High":4.741,"Low":4.572,"Close":4.643,"Volume":245590.3,"quote_asset_volume":"1144213.83490000","NumTrades":11895,"taker_buy_base_asset_volume":"105430.20000000","taker_buy_quote_asset_volume":"491265.18140000"},{"timestamp":1706486400000,"Open":"4.63200000","High":4.749,"Low":4.597,"Close":4.686,"Volume":232800.1,"quote_asset_volume":"1088783.04760000","NumTrades":11197,"taker_buy_base_asset_volume":"119560.30000000","taker_buy_quote_asset_volume":"559195.79260000"},{"timestamp":1706572800000,"Open":"4.67900000","High":4.925,"Low":4.659,"Close":4.702,"Volume":532812.7,"quote_asset_volume":"2544865.04820000","NumTrades":22893,"taker_buy_base_asset_volume":"262528.10000000","taker_buy_quote_asset_volume":"1254728.20420000"},{"timestamp":1706659200000,"Open":"4.70100000","High":4.782,"Low":4.56,"Close":4.626,"Volume":251988.6,"quote_asset_volume":"1177405.42850000","NumTrades":11962,"taker_buy_base_asset_volume":"115543.30000000","taker_buy_quote_asset_volume":"540374.79860000"},{"timestamp":1706745600000,"Open":"4.62700000","High":4.851,"Low":4.509,"Close":4.708,"Volume":463517.8,"quote_asset_volume":"2165495.94600000","NumTrades":24360,"taker_buy_base_asset_volume":"229621.60000000","taker_buy_quote_asset_volume":"1075797.82770000"},{"timestamp":1706832000000,"Open":"4.70200000","High":4.725,"Low":4.63,"Close":4.684,"Volume":141203.3,"quote_asset_volume":"659723.12590000","NumTrades":6917,"taker_buy_base_asset_volume":"69631.90000000","taker_buy_quote_asset_volume":"325308.37360000"},{"timestamp":1706918400000,"Open":"4.68700000","High":4.749,"Low":4.612,"Close":4.652,"Volume":143154.9,"quote_asset_volume":"668688.95030000","NumTrades":7467,"taker_buy_base_asset_volume":"61021.60000000","taker_buy_quote_asset_volume":"285225.90770000"},{"timestamp":1707004800000,"Open":"4.65000000","High":4.75,"Low":4.603,"Close":4.651,"Volume":156631.3,"quote_asset_volume":"730564.53470000","NumTrades":7994,"taker_buy_base_asset_volume":"72103.40000000","taker_buy_quote_asset_volume":"336781.78240000"},{"timestamp":1707091200000,"Open":"4.65100000","High":4.689,"Low":4.599,"Close":4.634,"Volume":107001.8,"quote_asset_volume":"496487.36600000","NumTrades":5603,"taker_buy_base_asset_volume":"40500.10000000","taker_buy_quote_asset_volume":"187982.65800000"},{"timestamp":1707177600000,"Open":"4.63400000","High":4.724,"Low":4.612,"Close":4.644,"Volume":175286.8,"quote_asset_volume":"816942.83680000","NumTrades":6700,"taker_buy_base_asset_volume":"84956.10000000","taker_buy_quote_asset_volume":"396161.27840000"},{"timestamp":1707264000000,"Open":"4.64500000","High":4.715,"Low":4.628,"Close":4.689,"Volume":112653.8,"quote_asset_volume":"525793.36020000","NumTrades":6070,"taker_buy_base_asset_volume":"53726.60000000","taker_buy_quote_asset_volume":"251069.82360000"},{"timestamp":1707350400000,"Open":"4.69500000","High":4.92,"Low":4.53,"Close":4.658,"Volume":381080.3,"quote_asset_volume":"1804672.30850000","NumTrades":15378,"taker_buy_base_asset_volume":"183611.50000000","taker_buy_quote_asset_volume":"872649.32550000"},{"timestamp":1707436800000,"Open":"4.65200000","High":4.776,"Low":4.638,"Close":4.762,"Volume":217097.7,"quote_asset_volume":"1025342.21400000","NumTrades":9680,"taker_buy_base_asset_volume":"93543.70000000","taker_buy_quote_asset_volume":"441808.30080000"},{"timestamp":1707523200000,"Open":"4.76000000","High":4.854,"Low":4.71,"Close":4.776,"Volume":164544.3,"quote_asset_volume":"784270.33180000","NumTrades":8006,"taker_buy_base_asset_volume":"86799.60000000","taker_buy_quote_asset_volume":"413845.28700000"},{"timestamp":1707609600000,"Open":"4.77600000","High":5.065,"Low":4.74,"Close":4.817,"Volume":529367.8,"quote_asset_volume":"2587871.33930000","NumTrades":25219,"taker_buy_base_asset_volume":"257208.30000000","taker_buy_quote_asset_volume":"1258133.54360000"},{"timestamp":1707696000000,"Open":"4.82000000","High":5.098,"Low":4.78,"Close":4.881,"Volume":638962.8,"quote_asset_volume":"3154164.34700000","NumTrades":33520,"taker_buy_base_asset_volume":"299171.00000000","taker_buy_quote_asset_volume":"1479391.74170000"},{"timestamp":1707782400000,"Open":"4.87900000","High":4.937,"Low":4.851,"Close":4.894,"Volume":181377.7,"quote_asset_volume":"887656.75430000","NumTrades":9537,"taker_buy_base_asset_volume":"77686.60000000","taker_buy_quote_asset_volume":"380514.02270000"},{"timestamp":1707868800000,"Open":"4.89400000","High":4.987,"Low":4.853,"Close":4.916,"Volume":194243.7,"quote_asset_volume":"956273.59010000","NumTrades":10907,"taker_buy_base_asset_volume":"90902.60000000","taker_buy_quote_asset_volume":"447907.56690000"},{"timestamp":1707955200000,"Open":"4.91200000","High":4.99,"Low":4.86,"Close":4.911,"Volume":344253.2,"quote_asset_volume":"1691843.08540000","NumTrades":15736,"taker_buy_base_asset_volume":"179757.60000000","taker_buy_quote_asset_volume":"883503.01780000"},{"timestamp":1708041600000,"Open":"4.91600000","High":5.384,"Low":4.872,"Close":5.29,"Volume":1025715.8,"quote_asset_volume":"5249783.98920000","NumTrades":51887,"taker_buy_base_asset_volume":"537267.70000000","taker_buy_quote_asset_volume":"2752216.99400000"},{"timestamp":1708128000000,"Open":"5.29000000","High":6.295,"Low":5.133,"Close":5.242,"Volume":3510240.3999999999,"quote_asset_volume":"19840963.49120000","NumTrades":176890,"taker_buy_base_asset_volume":"1780658.70000000","taker_buy_quote_asset_volume":"10070976.06420000"},{"timestamp":1708214400000,"Open":"5.24400000","High":5.373,"Low":5.103,"Close":5.163,"Volume":572736.7,"quote_asset_volume":"3001275.70450000","NumTrades":37490,"taker_buy_base_asset_volume":"283964.60000000","taker_buy_quote_asset_volume":"1490312.91010000"},{"timestamp":1708300800000,"Open":"5.16400000","High":5.3,"Low":5.11,"Close":5.229,"Volume":487693.1,"quote_asset_volume":"2536776.63800000","NumTrades":22456,"taker_buy_base_asset_volume":"232736.40000000","taker_buy_quote_asset_volume":"1211376.31840000"},{"timestamp":1708387200000,"Open":"5.22900000","High":5.417,"Low":5.059,"Close":5.195,"Volume":718066.6,"quote_asset_volume":"3743989.15410000","NumTrades":33598,"taker_buy_base_asset_volume":"359542.10000000","taker_buy_quote_asset_volume":"1875208.47000000"},{"timestamp":1708473600000,"Open":"5.19400000","High":5.4,"Low":5.05,"Close":5.224,"Volume":505920.9,"quote_asset_volume":"2635724.43100000","NumTrades":25238,"taker_buy_base_asset_volume":"255553.10000000","taker_buy_quote_asset_volume":"1331912.64220000"},{"timestamp":1708560000000,"Open":"5.22100000","High":5.238,"Low":4.954,"Close":5.033,"Volume":457678.1,"quote_asset_volume":"2334945.70180000","NumTrades":19900,"taker_buy_base_asset_volume":"178946.40000000","taker_buy_quote_asset_volume":"913807.16740000"},{"timestamp":1708646400000,"Open":"5.03000000","High":5.078,"Low":4.925,"Close":4.968,"Volume":292829.0,"quote_asset_volume":"1459839.30640000","NumTrades":14997,"taker_buy_base_asset_volume":"139011.80000000","taker_buy_quote_asset_volume":"693316.63980000"},{"timestamp":1708732800000,"Open":"4.96900000","High":5.1,"Low":4.89,"Close":5.031,"Volume":173360.8,"quote_asset_volume":"867551.43500000","NumTrades":8284,"taker_buy_base_asset_volume":"84980.60000000","taker_buy_quote_asset_volume":"425877.98150000"},{"timestamp":1708819200000,"Open":"5.03400000","High":5.205,"Low":5.015,"Close":5.136,"Volume":512561.0,"quote_asset_volume":"2604402.38140000","NumTrades":19577,"taker_buy_base_asset_volume":"306909.10000000","taker_buy_quote_asset_volume":"1559465.36770000"},{"timestamp":1708905600000,"Open":"5.13600000","High":5.183,"Low":4.96,"Close":5.111,"Volume":398391.1,"quote_asset_volume":"2020838.32730000","NumTrades":15241,"taker_buy_base_asset_volume":"182463.00000000","taker_buy_quote_asset_volume":"925325.16500000"},{"timestamp":1708992000000,"Open":"5.11100000","High":5.329,"Low":5.046,"Close":5.207,"Volume":452391.5,"quote_asset_volume":"2352121.84600000","NumTrades":21205,"taker_buy_base_asset_volume":"233041.80000000","taker_buy_quote_asset_volume":"1212388.93350000"},{"timestamp":1709078400000,"Open":"5.20700000","High":5.4,"Low":4.893,"Close":5.126,"Volume":1567139.2,"quote_asset_volume":"8052011.58410000","NumTrades":71324,"taker_buy_base_asset_volume":"765804.70000000","taker_buy_quote_asset_volume":"3939187.85700000"},{"timestamp":1709164800000,"Open":"5.13100000","High":5.279,"Low":5.101,"Close":5.195,"Volume":888251.5,"quote_asset_volume":"4593645.33130000","NumTrades":34339,"taker_buy_base_asset_volume":"442833.00000000","taker_buy_quote_asset_volume":"2292102.16560000"},{"timestamp":1709251200000,"Open":"5.19500000","High":5.431,"Low":5.18,"Close":5.364,"Volume":564234.1,"quote_asset_volume":"2997777.63380000","NumTrades":25217,"taker_buy_base_asset_volume":"282671.50000000","taker_buy_quote_asset_volume":"1502348.65910000"},{"timestamp":1709337600000,"Open":"5.36600000","High":6.067,"Low":5.281,"Close":5.737,"Volume":986409.1,"quote_asset_volume":"5551774.41830000","NumTrades":53003,"taker_buy_base_asset_volume":"527583.70000000","taker_buy_quote_asset_volume":"2973153.57020000"},{"timestamp":1709424000000,"Open":"5.73700000","High":5.873,"Low":5.4,"Close":5.602,"Volume":553912.9,"quote_asset_volume":"3109720.40880000","NumTrades":31762,"taker_buy_base_asset_volume":"265210.40000000","taker_buy_quote_asset_volume":"1489883.13670000"},{"timestamp":1709510400000,"Open":"5.60200000","High":5.873,"Low":5.414,"Close":5.534,"Volume":576886.8,"quote_asset_volume":"3210953.81960000","NumTrades":33673,"taker_buy_base_asset_volume":"271218.10000000","taker_buy_quote_asset_volume":"1511875.52470000"},{"timestamp":1709596800000,"Open":"5.53300000","High":5.749,"Low":5.01,"Close":5.262,"Volume":888493.5,"quote_asset_volume":"4826877.17090000","NumTrades":57544,"taker_buy_base_asset_volume":"417653.80000000","taker_buy_quote_asset_volume":"2272029.06480000"},{"timestamp":1709683200000,"Open":"5.27100000","High":5.536,"Low":5.17,"Close":5.404,"Volume":542373.6,"quote_asset_volume":"2903154.43780000","NumTrades":40200,"taker_buy_base_asset_volume":"281227.50000000","taker_buy_quote_asset_volume":"1506559.75070000"},{"timestamp":1709769600000,"Open":"5.40500000","High":5.569,"Low":5.341,"Close":5.502,"Volume":413873.6,"quote_asset_volume":"2266240.05160000","NumTrades":30478,"taker_buy_base_asset_volume":"206621.60000000","taker_buy_quote_asset_volume":"1131651.58510000"},{"timestamp":1709856000000,"Open":"5.50300000","High":6.75,"Low":5.428,"Close":6.14,"Volume":3005049.5,"quote_asset_volume":"18132225.75810000","NumTrades":220319,"taker_buy_base_asset_volume":"1501568.60000000","taker_buy_quote_asset_volume":"9070624.63930000"},{"timestamp":1709942400000,"Open":"6.14300000","High":6.202,"Low":5.849,"Close":5.943,"Volume":811221.0,"quote_asset_volume":"4855376.40290000","NumTrades":64425,"taker_buy_base_asset_volume":"390762.30000000","taker_buy_quote_asset_volume":"2339446.77570000"},{"timestamp":1710028800000,"Open":"5.94200000","High":5.957,"Low":5.557,"Close":5.713,"Volume":653329.3,"quote_asset_volume":"3766567.78450000","NumTrades":46530,"taker_buy_base_asset_volume":"300277.20000000","taker_buy_quote_asset_volume":"1732760.40640000"},{"timestamp":1710115200000,"Open":"5.71500000","High":6.171,"Low":5.51,"Close":5.976,"Volume":953813.1,"quote_asset_volume":"5609177.53740000","NumTrades":71494,"taker_buy_base_asset_volume":"478808.00000000","taker_buy_quote_asset_volume":"2817161.73930000"},{"timestamp":1710201600000,"Open":"5.97700000","High":6.024,"Low":5.636,"Close":6.011,"Volume":757731.4,"quote_asset_volume":"4449740.52900000","NumTrades":54544,"taker_buy_base_asset_volume":"356871.30000000","taker_buy_quote_asset_volume":"2097632.57180000"},{"timestamp":1710288000000,"Open":"6.00700000","High":6.331,"Low":5.851,"Close":6.105,"Volume":927235.7,"quote_asset_volume":"5656850.33450000","NumTrades":80203,"taker_buy_base_asset_volume":"475536.40000000","taker_buy_quote_asset_volume":"2901710.91610000"},{"timestamp":1710374400000,"Open":"6.10700000","High":6.97,"Low":5.879,"Close":6.662,"Volume":2117333.0,"quote_asset_volume":"13515990.71870000","NumTrades":202721,"taker_buy_base_asset_volume":"1071690.80000000","taker_buy_quote_asset_volume":"6850940.70960000"},{"timestamp":1710460800000,"Open":"6.66300000","High":7.875,"Low":6.143,"Close":6.315,"Volume":5050546.2999999998,"quote_asset_volume":"35105460.27500000","NumTrades":429854,"taker_buy_base_asset_volume":"2505490.60000000","taker_buy_quote_asset_volume":"17448314.45240000"},{"timestamp":1710547200000,"Open":"6.31600000","High":6.373,"Low":5.501,"Close":5.67,"Volume":1095398.5,"quote_asset_volume":"6640502.74810000","NumTrades":82858,"taker_buy_base_asset_volume":"503189.00000000","taker_buy_quote_asset_volume":"3058004.01840000"},{"timestamp":1710633600000,"Open":"5.67000000","High":5.83,"Low":5.288,"Close":5.665,"Volume":754966.3,"quote_asset_volume":"4263199.20350000","NumTrades":47723,"taker_buy_base_asset_volume":"372015.00000000","taker_buy_quote_asset_volume":"2100912.35560000"},{"timestamp":1710720000000,"Open":"5.66300000","High":6.132,"Low":5.466,"Close":5.548,"Volume":677766.8,"quote_asset_volume":"3876525.75970000","NumTrades":51184,"taker_buy_base_asset_volume":"328877.60000000","taker_buy_quote_asset_volume":"1885332.19160000"},{"timestamp":1710806400000,"Open":"5.55200000","High":5.631,"Low":4.848,"Close":4.941,"Volume":917385.4,"quote_asset_volume":"4703915.96150000","NumTrades":45654,"taker_buy_base_asset_volume":"437911.70000000","taker_buy_quote_asset_volume":"2243776.10160000"},{"timestamp":1710892800000,"Open":"4.94100000","High":5.424,"Low":4.896,"Close":5.361,"Volume":977165.1,"quote_asset_volume":"5034816.43730000","NumTrades":52634,"taker_buy_base_asset_volume":"464315.20000000","taker_buy_quote_asset_volume":"2392268.96720000"},{"timestamp":1710979200000,"Open":"5.36000000","High":5.529,"Low":5.244,"Close":5.397,"Volume":415087.3,"quote_asset_volume":"2241837.90520000","NumTrades":30652,"taker_buy_base_asset_volume":"214532.90000000","taker_buy_quote_asset_volume":"1159945.74110000"},{"timestamp":1711065600000,"Open":"5.40000000","High":5.608,"Low":5.295,"Close":5.492,"Volume":650594.4,"quote_asset_volume":"3539736.17130000","NumTrades":40280,"taker_buy_base_asset_volume":"317604.80000000","taker_buy_quote_asset_volume":"1730796.36990000"},{"timestamp":1711152000000,"Open":"5.49100000","High":5.813,"Low":5.458,"Close":5.599,"Volume":553153.3,"quote_asset_volume":"3114538.61850000","NumTrades":30935,"taker_buy_base_asset_volume":"263562.10000000","taker_buy_quote_asset_volume":"1486161.57320000"},{"timestamp":1711238400000,"Open":"5.59900000","High":5.716,"Low":5.535,"Close":5.704,"Volume":254103.1,"quote_asset_volume":"1427782.16230000","NumTrades":13202,"taker_buy_base_asset_volume":"123373.30000000","taker_buy_quote_asset_volume":"693588.80210000"},{"timestamp":1711324800000,"Open":"5.70000000","High":5.88,"Low":5.584,"Close":5.856,"Volume":414606.6,"quote_asset_volume":"2365980.80810000","NumTrades":24090,"taker_buy_base_asset_volume":"216216.40000000","taker_buy_quote_asset_volume":"1234244.98730000"},{"timestamp":1711411200000,"Open":"5.85600000","High":6.025,"Low":5.753,"Close":5.938,"Volume":419951.0,"quote_asset_volume":"2477847.28780000","NumTrades":27890,"taker_buy_base_asset_volume":"201941.60000000","taker_buy_quote_asset_volume":"1192462.47740000"},{"timestamp":1711497600000,"Open":"5.93200000","High":6.16,"Low":5.781,"Close":5.813,"Volume":456745.2,"quote_asset_volume":"2730492.26510000","NumTrades":35734,"taker_buy_base_asset_volume":"224333.00000000","taker_buy_quote_asset_volume":"1342577.21800000"},{"timestamp":1711584000000,"Open":"5.81400000","High":6.067,"Low":5.71,"Close":6.02,"Volume":337843.4,"quote_asset_volume":"1989898.15860000","NumTrades":24762,"taker_buy_base_asset_volume":"170422.80000000","taker_buy_quote_asset_volume":"1004409.68110000"},{"timestamp":1711670400000,"Open":"6.02000000","High":6.067,"Low":5.81,"Close":5.906,"Volume":209712.4,"quote_asset_volume":"1241047.16800000","NumTrades":18888,"taker_buy_base_asset_volume":"98132.40000000","taker_buy_quote_asset_volume":"580907.88830000"},{"timestamp":1711756800000,"Open":"5.90600000","High":5.97,"Low":5.839,"Close":5.903,"Volume":186825.3,"quote_asset_volume":"1104433.83590000","NumTrades":23076,"taker_buy_base_asset_volume":"89874.00000000","taker_buy_quote_asset_volume":"531245.63860000"},{"timestamp":1711843200000,"Open":"5.90300000","High":6.012,"Low":5.852,"Close":6.012,"Volume":216300.2,"quote_asset_volume":"1282319.74490000","NumTrades":19235,"taker_buy_base_asset_volume":"111181.10000000","taker_buy_quote_asset_volume":"659801.58410000"},{"timestamp":1711929600000,"Open":"6.01100000","High":6.015,"Low":5.626,"Close":5.776,"Volume":490008.2,"quote_asset_volume":"2823757.55150000","NumTrades":37728,"taker_buy_base_asset_volume":"225883.40000000","taker_buy_quote_asset_volume":"1302305.20510000"},{"timestamp":1712016000000,"Open":"5.77600000","High":5.793,"Low":5.259,"Close":5.387,"Volume":500494.2,"quote_asset_volume":"2739901.05750000","NumTrades":42613,"taker_buy_base_asset_volume":"240896.90000000","taker_buy_quote_asset_volume":"1317906.18350000"},{"timestamp":1712102400000,"Open":"5.38700000","High":5.863,"Low":5.22,"Close":5.705,"Volume":855715.3,"quote_asset_volume":"4805331.55420000","NumTrades":70703,"taker_buy_base_asset_volume":"438266.90000000","taker_buy_quote_asset_volume":"2464309.30670000"},{"timestamp":1712188800000,"Open":"5.70500000","High":6.45,"Low":5.656,"Close":5.769,"Volume":2474272.5,"quote_asset_volume":"14954276.31980000","NumTrades":168484,"taker_buy_base_asset_volume":"1267638.60000000","taker_buy_quote_asset_volume":"7678187.93070000"},{"timestamp":1712275200000,"Open":"5.77100000","High":6.328,"Low":5.676,"Close":5.915,"Volume":854119.8,"quote_asset_volume":"5091173.60890000","NumTrades":66100,"taker_buy_base_asset_volume":"409725.70000000","taker_buy_quote_asset_volume":"2449430.54880000"},{"timestamp":1712361600000,"Open":"5.91400000","High":6.182,"Low":5.899,"Close":5.918,"Volume":340761.1,"quote_asset_volume":"2051706.65300000","NumTrades":29425,"taker_buy_base_asset_volume":"164697.80000000","taker_buy_quote_asset_volume":"992470.32170000"},{"timestamp":1712448000000,"Open":"5.92200000","High":6.124,"Low":5.86,"Close":6.099,"Volume":336678.7,"quote_asset_volume":"2006456.58990000","NumTrades":26942,"taker_buy_base_asset_volume":"167772.70000000","taker_buy_quote_asset_volume":"1001422.13330000"},{"timestamp":1712534400000,"Open":"6.10000000","High":6.404,"Low":6.1,"Close":6.147,"Volume":580353.4,"quote_asset_volume":"3629613.57160000","NumTrades":45903,"taker_buy_base_asset_volume":"284789.10000000","taker_buy_quote_asset_volume":"1783678.00750000"},{"timestamp":1712620800000,"Open":"6.14600000","High":6.24,"Low":5.936,"Close":6.015,"Volume":286469.6,"quote_asset_volume":"1747957.41080000","NumTrades":25064,"taker_buy_base_asset_volume":"144844.70000000","taker_buy_quote_asset_volume":"884473.89230000"},{"timestamp":1712707200000,"Open":"6.01800000","High":6.45,"Low":5.928,"Close":6.074,"Volume":1147233.6000000001,"quote_asset_volume":"7153071.58410000","NumTrades":60489,"taker_buy_base_asset_volume":"572780.40000000","taker_buy_quote_asset_volume":"3578690.66990000"},{"timestamp":1712793600000,"Open":"6.07400000","High":6.119,"Low":5.819,"Close":5.994,"Volume":435825.1,"quote_asset_volume":"2605014.03180000","NumTrades":28105,"taker_buy_base_asset_volume":"208409.00000000","taker_buy_quote_asset_volume":"1247149.18850000"},{"timestamp":1712880000000,"Open":"5.99700000","High":6.12,"Low":4.783,"Close":4.969,"Volume":519651.9,"quote_asset_volume":"2825309.21700000","NumTrades":34825,"taker_buy_base_asset_volume":"222589.20000000","taker_buy_quote_asset_volume":"1208433.47220000"},{"timestamp":1712966400000,"Open":"4.96900000","High":5.415,"Low":4.0,"Close":4.347,"Volume":892618.8,"quote_asset_volume":"4268497.78020000","NumTrades":58346,"taker_buy_base_asset_volume":"434249.50000000","taker_buy_quote_asset_volume":"2082961.98900000"},{"timestamp":1713052800000,"Open":"4.34700000","High":4.681,"Low":4.143,"Close":4.649,"Volume":700024.3,"quote_asset_volume":"3086157.48420000","NumTrades":50778,"taker_buy_base_asset_volume":"360715.50000000","taker_buy_quote_asset_volume":"1590865.52240000"},{"timestamp":1713139200000,"Open":"4.64600000","High":4.762,"Low":4.37,"Close":4.447,"Volume":633749.9,"quote_asset_volume":"2889650.39010000","NumTrades":39159,"taker_buy_base_asset_volume":"306163.40000000","taker_buy_quote_asset_volume":"1396424.01270000"},{"timestamp":1713225600000,"Open":"4.44700000","High":5.111,"Low":4.236,"Close":4.726,"Volume":1351290.3,"quote_asset_volume":"6367786.49670000","NumTrades":66820,"taker_buy_base_asset_volume":"686003.10000000","taker_buy_quote_asset_volume":"3240561.93820000"},{"timestamp":1713312000000,"Open":"4.73100000","High":5.047,"Low":4.501,"Close":4.665,"Volume":805713.6,"quote_asset_volume":"3846982.84750000","NumTrades":42897,"taker_buy_base_asset_volume":"393946.20000000","taker_buy_quote_asset_volume":"1885279.02040000"},{"timestamp":1713398400000,"Open":"4.66300000","High":4.785,"Low":4.603,"Close":4.674,"Volume":263443.0,"quote_asset_volume":"1238137.78470000","NumTrades":15897,"taker_buy_base_asset_volume":"123679.00000000","taker_buy_quote_asset_volume":"581288.84500000"},{"timestamp":1713484800000,"Open":"4.67000000","High":4.841,"Low":4.466,"Close":4.726,"Volume":296475.4,"quote_asset_volume":"1398420.56770000","NumTrades":16682,"taker_buy_base_asset_volume":"146768.20000000","taker_buy_quote_asset_volume":"691141.06550000"},{"timestamp":1713571200000,"Open":"4.72900000","High":4.997,"Low":4.69,"Close":4.952,"Volume":344106.7,"quote_asset_volume":"1674303.75630000","NumTrades":19439,"taker_buy_base_asset_volume":"176776.10000000","taker_buy_quote_asset_volume":"861386.18910000"},{"timestamp":1713657600000,"Open":"4.95000000","High":4.999,"Low":4.79,"Close":4.905,"Volume":214463.6,"quote_asset_volume":"1053635.75540000","NumTrades":17961,"taker_buy_base_asset_volume":"108644.60000000","taker_buy_quote_asset_volume":"534323.31130000"},{"timestamp":1713744000000,"Open":"4.90500000","High":5.038,"Low":4.876,"Close":4.973,"Volume":269070.5,"quote_asset_volume":"1338690.63080000","NumTrades":17876,"taker_buy_base_asset_volume":"132247.00000000","taker_buy_quote_asset_volume":"658209.87750000"},{"timestamp":1713830400000,"Open":"4.97400000","High":5.116,"Low":4.921,"Close":4.943,"Volume":362699.9,"quote_asset_volume":"1815892.21470000","NumTrades":21365,"taker_buy_base_asset_volume":"174195.80000000","taker_buy_quote_asset_volume":"872391.50120000"},{"timestamp":1713916800000,"Open":"4.94800000","High":5.1,"Low":4.779,"Close":4.862,"Volume":410085.6,"quote_asset_volume":"2026599.34160000","NumTrades":35337,"taker_buy_base_asset_volume":"214379.80000000","taker_buy_quote_asset_volume":"1060330.97390000"},{"timestamp":1714003200000,"Open":"4.86100000","High":4.98,"Low":4.695,"Close":4.796,"Volume":410233.7,"quote_asset_volume":"1984928.45240000","NumTrades":33092,"taker_buy_base_asset_volume":"206632.80000000","taker_buy_quote_asset_volume":"1001317.62790000"},{"timestamp":1714089600000,"Open":"4.79600000","High":4.819,"Low":4.646,"Close":4.692,"Volume":250281.2,"quote_asset_volume":"1182187.67740000","NumTrades":18610,"taker_buy_base_asset_volume":"115085.10000000","taker_buy_quote_asset_volume":"543498.81900000"},{"timestamp":1714176000000,"Open":"4.69300000","High":4.748,"Low":4.432,"Close":4.563,"Volume":286158.2,"quote_asset_volume":"1302585.06920000","NumTrades":15141,"taker_buy_base_asset_volume":"130913.60000000","taker_buy_quote_asset_volume":"594667.00900000"},{"timestamp":1714262400000,"Open":"4.56000000","High":4.71,"Low":4.439,"Close":4.439,"Volume":207427.8,"quote_asset_volume":"948500.59770000","NumTrades":12838,"taker_buy_base_asset_volume":"101844.90000000","taker_buy_quote_asset_volume":"465268.20180000"},{"timestamp":1714348800000,"Open":"4.44100000","High":4.575,"Low":4.336,"Close":4.506,"Volume":297604.6,"quote_asset_volume":"1326276.58470000","NumTrades":15325,"taker_buy_base_asset_volume":"148316.40000000","taker_buy_quote_asset_volume":"661216.68720000"},{"timestamp":1714435200000,"Open":"4.50600000","High":4.546,"Low":4.051,"Close":4.25,"Volume":468016.5,"quote_asset_volume":"2008742.61480000","NumTrades":20385,"taker_buy_base_asset_volume":"238356.80000000","taker_buy_quote_asset_volume":"1027182.06460000"},{"timestamp":1714521600000,"Open":"4.25000000","High":4.386,"Low":4.0,"Close":4.302,"Volume":497122.6,"quote_asset_volume":"2096516.42120000","NumTrades":19923,"taker_buy_base_asset_volume":"239823.40000000","taker_buy_quote_asset_volume":"1011601.89590000"},{"timestamp":1714608000000,"Open":"4.30700000","High":4.484,"Low":4.212,"Close":4.44,"Volume":313954.1,"quote_asset_volume":"1373343.90550000","NumTrades":12807,"taker_buy_base_asset_volume":"158776.30000000","taker_buy_quote_asset_volume":"694511.89450000"},{"timestamp":1714694400000,"Open":"4.43900000","High":4.656,"Low":4.411,"Close":4.618,"Volume":370505.1,"quote_asset_volume":"1682467.63790000","NumTrades":23660,"taker_buy_base_asset_volume":"190585.90000000","taker_buy_quote_asset_volume":"865511.13770000"},{"timestamp":1714780800000,"Open":"4.61800000","High":4.659,"Low":4.493,"Close":4.565,"Volume":350957.9,"quote_asset_volume":"1608361.66000000","NumTrades":25082,"taker_buy_base_asset_volume":"161237.10000000","taker_buy_quote_asset_volume":"739817.52530000"},{"timestamp":1714867200000,"Open":"4.56000000","High":4.575,"Low":4.456,"Close":4.523,"Volume":271385.6,"quote_asset_volume":"1224282.43130000","NumTrades":14924,"taker_buy_base_asset_volume":"138977.00000000","taker_buy_quote_asset_volume":"627034.81230000"},{"timestamp":1714953600000,"Open":"4.52000000","High":4.689,"Low":4.47,"Close":4.505,"Volume":269330.6,"quote_asset_volume":"1224632.12010000","NumTrades":19621,"taker_buy_base_asset_volume":"137890.00000000","taker_buy_quote_asset_volume":"627215.23730000"},{"timestamp":1715040000000,"Open":"4.50100000","High":4.649,"Low":4.445,"Close":4.502,"Volume":329972.5,"quote_asset_volume":"1508021.73440000","NumTrades":19102,"taker_buy_base_asset_volume":"154059.40000000","taker_buy_quote_asset_volume":"703939.97630000"},{"timestamp":1715126400000,"Open":"4.49900000","High":4.528,"Low":4.304,"Close":4.51,"Volume":275777.7,"quote_asset_volume":"1219988.27850000","NumTrades":17505,"taker_buy_base_asset_volume":"130274.20000000","taker_buy_quote_asset_volume":"576541.62810000"},{"timestamp":1715212800000,"Open":"4.51000000","High":4.642,"Low":4.301,"Close":4.529,"Volume":591182.2,"quote_asset_volume":"2622482.36020000","NumTrades":31833,"taker_buy_base_asset_volume":"302908.40000000","taker_buy_quote_asset_volume":"1344063.85160000"},{"timestamp":1715299200000,"Open":"4.52900000","High":4.744,"Low":4.369,"Close":4.632,"Volume":938028.9,"quote_asset_volume":"4253048.85180000","NumTrades":41099,"taker_buy_base_asset_volume":"500742.70000000","taker_buy_quote_asset_volume":"2271656.52420000"},{"timestamp":1715385600000,"Open":"4.63100000","High":4.9,"Low":4.383,"Close":4.519,"Volume":1102079.5,"quote_asset_volume":"5045723.03190000","NumTrades":47701,"taker_buy_base_asset_volume":"544142.30000000","taker_buy_quote_asset_volume":"2496670.93610000"},{"timestamp":1715472000000,"Open":"4.52300000","High":4.672,"Low":4.423,"Close":4.45,"Volume":412762.0,"quote_asset_volume":"1862590.29850000","NumTrades":19130,"taker_buy_base_asset_volume":"197910.60000000","taker_buy_quote_asset_volume":"893264.06710000"},{"timestamp":1715558400000,"Open":"4.45600000","High":4.537,"Low":4.301,"Close":4.371,"Volume":343106.0,"quote_asset_volume":"1508247.21810000","NumTrades":17847,"taker_buy_base_asset_volume":"149302.20000000","taker_buy_quote_asset_volume":"656721.02850000"},{"timestamp":1715644800000,"Open":"4.36400000","High":4.413,"Low":4.053,"Close":4.115,"Volume":466486.7,"quote_asset_volume":"1953272.34020000","NumTrades":23993,"taker_buy_base_asset_volume":"209859.80000000","taker_buy_quote_asset_volume":"878250.82120000"},{"timestamp":1715731200000,"Open":"4.11300000","High":4.319,"Low":4.065,"Close":4.286,"Volume":251735.5,"quote_asset_volume":"1051321.44200000","NumTrades":13823,"taker_buy_base_asset_volume":"120347.40000000","taker_buy_quote_asset_volume":"502856.64340000"},{"timestamp":1715817600000,"Open":"4.28400000","High":4.339,"Low":4.122,"Close":4.279,"Volume":159150.8,"quote_asset_volume":"676485.01450000","NumTrades":12421,"taker_buy_base_asset_volume":"81388.10000000","taker_buy_quote_asset_volume":"346516.81100000"},{"timestamp":1715904000000,"Open":"4.28000000","High":4.413,"Low":4.244,"Close":4.369,"Volume":168593.6,"quote_asset_volume":"730076.07730000","NumTrades":12187,"taker_buy_base_asset_volume":"90392.00000000","taker_buy_quote_asset_volume":"391599.72400000"},{"timestamp":1715990400000,"Open":"4.36900000","High":4.443,"Low":4.324,"Close":4.425,"Volume":126488.9,"quote_asset_volume":"554384.23740000","NumTrades":14318,"taker_buy_base_asset_volume":"65292.00000000","taker_buy_quote_asset_volume":"286518.68450000"},{"timestamp":1716076800000,"Open":"4.42400000","High":4.475,"Low":4.216,"Close":4.298,"Volume":241872.6,"quote_asset_volume":"1049687.74840000","NumTrades":25423,"taker_buy_base_asset_volume":"120183.60000000","taker_buy_quote_asset_volume":"521986.31980000"},{"timestamp":1716163200000,"Open":"4.29800000","High":4.55,"Low":4.255,"Close":4.51,"Volume":328436.6,"quote_asset_volume":"1454259.59750000","NumTrades":37792,"taker_buy_base_asset_volume":"177102.90000000","taker_buy_quote_asset_volume":"785115.25200000"},{"timestamp":1716249600000,"Open":"4.51100000","High":4.543,"Low":4.391,"Close":4.426,"Volume":381751.5,"quote_asset_volume":"1714082.35610000","NumTrades":38688,"taker_buy_base_asset_volume":"172544.00000000","taker_buy_quote_asset_volume":"774992.15010000"},{"timestamp":1716336000000,"Open":"4.43200000","High":4.482,"Low":4.304,"Close":4.366,"Volume":226128.2,"quote_asset_volume":"988796.93530000","NumTrades":21136,"taker_buy_base_asset_volume":"108369.40000000","taker_buy_quote_asset_volume":"474004.26570000"},{"timestamp":1716422400000,"Open":"4.36300000","High":4.399,"Low":4.14,"Close":4.237,"Volume":328157.3,"quote_asset_volume":"1404602.80940000","NumTrades":24371,"taker_buy_base_asset_volume":"158799.80000000","taker_buy_quote_asset_volume":"680073.77860000"},{"timestamp":1716508800000,"Open":"4.23700000","High":4.327,"Low":4.169,"Close":4.259,"Volume":175835.6,"quote_asset_volume":"745995.72580000","NumTrades":16457,"taker_buy_base_asset_volume":"84070.90000000","taker_buy_quote_asset_volume":"357086.89550000"},{"timestamp":1716595200000,"Open":"4.26200000","High":4.601,"Low":4.248,"Close":4.491,"Volume":619562.7,"quote_asset_volume":"2740154.85760000","NumTrades":37827,"taker_buy_base_asset_volume":"331808.60000000","taker_buy_quote_asset_volume":"1468246.45780000"},{"timestamp":1716681600000,"Open":"4.49200000","High":4.679,"Low":4.255,"Close":4.305,"Volume":968180.1,"quote_asset_volume":"4346370.97080000","NumTrades":45113,"taker_buy_base_asset_volume":"442408.60000000","taker_buy_quote_asset_volume":"1992185.91630000"},{"timestamp":1716768000000,"Open":"4.30800000","High":4.421,"Low":4.265,"Close":4.399,"Volume":256472.1,"quote_asset_volume":"1113282.63040000","NumTrades":18210,"taker_buy_base_asset_volume":"132896.00000000","taker_buy_quote_asset_volume":"576877.11400000"},{"timestamp":1716854400000,"Open":"4.39900000","High":4.62,"Low":4.295,"Close":4.542,"Volume":556503.1,"quote_asset_volume":"2473278.42350000","NumTrades":28859,"taker_buy_base_asset_volume":"289717.90000000","taker_buy_quote_asset_volume":"1287857.22500000"},{"timestamp":1716940800000,"Open":"4.54400000","High":5.4,"Low":4.435,"Close":4.72,"Volume":2714046.7000000002,"quote_asset_volume":"13411772.47180000","NumTrades":134372,"taker_buy_base_asset_volume":"1407820.40000000","taker_buy_quote_asset_volume":"6962235.06720000"},{"timestamp":1717027200000,"Open":"4.71900000","High":4.791,"Low":4.392,"Close":4.476,"Volume":804561.7,"quote_asset_volume":"3655179.69380000","NumTrades":36374,"taker_buy_base_asset_volume":"349197.70000000","taker_buy_quote_asset_volume":"1587435.74760000"},{"timestamp":1717113600000,"Open":"4.47400000","High":4.701,"Low":4.403,"Close":4.524,"Volume":470511.3,"quote_asset_volume":"2139081.40150000","NumTrades":20909,"taker_buy_base_asset_volume":"233804.90000000","taker_buy_quote_asset_volume":"1065277.43340000"},{"timestamp":1717200000000,"Open":"4.51900000","High":4.617,"Low":4.48,"Close":4.491,"Volume":231513.1,"quote_asset_volume":"1048328.35340000","NumTrades":10710,"taker_buy_base_asset_volume":"100767.40000000","taker_buy_quote_asset_volume":"456773.49830000"},{"timestamp":1717286400000,"Open":"4.48900000","High":4.573,"Low":4.443,"Close":4.508,"Volume":282122.9,"quote_asset_volume":"1268537.36200000","NumTrades":15131,"taker_buy_base_asset_volume":"144000.90000000","taker_buy_quote_asset_volume":"648561.60190000"},{"timestamp":1717372800000,"Open":"4.51000000","High":4.628,"Low":4.476,"Close":4.49,"Volume":223313.4,"quote_asset_volume":"1014736.79850000","NumTrades":13288,"taker_buy_base_asset_volume":"108262.10000000","taker_buy_quote_asset_volume":"492132.39170000"},{"timestamp":1717459200000,"Open":"4.48800000","High":4.838,"Low":4.424,"Close":4.704,"Volume":504762.2,"quote_asset_volume":"2345067.85520000","NumTrades":22945,"taker_buy_base_asset_volume":"266423.10000000","taker_buy_quote_asset_volume":"1238639.70160000"},{"timestamp":1717545600000,"Open":"4.70300000","High":4.732,"Low":4.6,"Close":4.71,"Volume":294428.4,"quote_asset_volume":"1370860.19640000","NumTrades":15239,"taker_buy_base_asset_volume":"131321.00000000","taker_buy_quote_asset_volume":"611946.73450000"},{"timestamp":1717632000000,"Open":"4.70900000","High":4.744,"Low":4.587,"Close":4.695,"Volume":276463.3,"quote_asset_volume":"1291304.06060000","NumTrades":19225,"taker_buy_base_asset_volume":"134141.00000000","taker_buy_quote_asset_volume":"626837.95500000"},{"timestamp":1717718400000,"Open":"4.69500000","High":4.821,"Low":4.275,"Close":4.406,"Volume":390386.5,"quote_asset_volume":"1769886.21870000","NumTrades":24743,"taker_buy_base_asset_volume":"187197.50000000","taker_buy_quote_asset_volume":"850834.75010000"},{"timestamp":1717804800000,"Open":"4.40600000","High":4.468,"Low":4.241,"Close":4.258,"Volume":332119.6,"quote_asset_volume":"1448208.46090000","NumTrades":19454,"taker_buy_base_asset_volume":"160236.10000000","taker_buy_quote_asset_volume":"700191.05680000"},{"timestamp":1717891200000,"Open":"4.25800000","High":4.38,"Low":4.203,"Close":4.345,"Volume":229342.6,"quote_asset_volume":"986407.00420000","NumTrades":18197,"taker_buy_base_asset_volume":"107141.80000000","taker_buy_quote_asset_volume":"461385.27580000"},{"timestamp":1717977600000,"Open":"4.34600000","High":4.537,"Low":4.211,"Close":4.301,"Volume":432124.8,"quote_asset_volume":"1905184.05280000","NumTrades":28627,"taker_buy_base_asset_volume":"205273.30000000","taker_buy_quote_asset_volume":"907654.20260000"},{"timestamp":1718064000000,"Open":"4.30400000","High":4.381,"Low":4.054,"Close":4.149,"Volume":271793.2,"quote_asset_volume":"1143340.57420000","NumTrades":15745,"taker_buy_base_asset_volume":"123184.00000000","taker_buy_quote_asset_volume":"518275.57900000"},{"timestamp":1718150400000,"Open":"4.14900000","High":4.376,"Low":4.091,"Close":4.278,"Volume":211047.4,"quote_asset_volume":"905117.03100000","NumTrades":13073,"taker_buy_base_asset_volume":"102293.90000000","taker_buy_quote_asset_volume":"438311.57890000"},{"timestamp":1718236800000,"Open":"4.27800000","High":4.296,"Low":4.042,"Close":4.084,"Volume":233813.0,"quote_asset_volume":"968678.41640000","NumTrades":12182,"taker_buy_base_asset_volume":"111619.20000000","taker_buy_quote_asset_volume":"462695.72230000"},{"timestamp":1718323200000,"Open":"4.08300000","High":4.308,"Low":4.016,"Close":4.182,"Volume":574172.8,"quote_asset_volume":"2399595.96850000","NumTrades":26478,"taker_buy_base_asset_volume":"302549.90000000","taker_buy_quote_asset_volume":"1266292.73440000"},{"timestamp":1718409600000,"Open":"4.18200000","High":4.212,"Low":3.901,"Close":3.993,"Volume":484975.0,"quote_asset_volume":"1944436.99680000","NumTrades":18706,"taker_buy_base_asset_volume":"213751.20000000","taker_buy_quote_asset_volume":"857197.57140000"},{"timestamp":1718496000000,"Open":"3.99700000","High":4.04,"Low":3.912,"Close":3.961,"Volume":222998.2,"quote_asset_volume":"884476.00720000","NumTrades":9145,"taker_buy_base_asset_volume":"103927.10000000","taker_buy_quote_asset_volume":"412342.15220000"},{"timestamp":1718582400000,"Open":"3.96100000","High":3.971,"Low":3.39,"Close":3.452,"Volume":665128.8,"quote_asset_volume":"2358035.42170000","NumTrades":23270,"taker_buy_base_asset_volume":"323669.30000000","taker_buy_quote_asset_volume":"1143420.27380000"},{"timestamp":1718668800000,"Open":"3.45600000","High":3.468,"Low":3.074,"Close":3.281,"Volume":454984.6,"quote_asset_volume":"1458780.20400000","NumTrades":17443,"taker_buy_base_asset_volume":"215964.00000000","taker_buy_quote_asset_volume":"691390.02510000"},{"timestamp":1718755200000,"Open":"3.27700000","High":3.36,"Low":3.176,"Close":3.241,"Volume":175235.3,"quote_asset_volume":"572791.05070000","NumTrades":10521,"taker_buy_base_asset_volume":"88092.10000000","taker_buy_quote_asset_volume":"287765.87570000"},{"timestamp":1718841600000,"Open":"3.24300000","High":3.417,"Low":3.2,"Close":3.262,"Volume":250020.5,"quote_asset_volume":"823719.67500000","NumTrades":13101,"taker_buy_base_asset_volume":"113337.00000000","taker_buy_quote_asset_volume":"373956.82400000"},{"timestamp":1718928000000,"Open":"3.25800000","High":3.346,"Low":3.191,"Close":3.224,"Volume":474455.4,"quote_asset_volume":"1546973.53870000","NumTrades":19292,"taker_buy_base_asset_volume":"233160.50000000","taker_buy_quote_asset_volume":"760083.53790000"},{"timestamp":1719014400000,"Open":"3.22400000","High":3.244,"Low":3.162,"Close":3.233,"Volume":164708.2,"quote_asset_volume":"527925.83680000","NumTrades":9885,"taker_buy_base_asset_volume":"80698.30000000","taker_buy_quote_asset_volume":"258806.63390000"},{"timestamp":1719100800000,"Open":"3.23400000","High":3.282,"Low":3.069,"Close":3.085,"Volume":234648.1,"quote_asset_volume":"752759.49180000","NumTrades":10682,"taker_buy_base_asset_volume":"111222.40000000","taker_buy_quote_asset_volume":"357329.27750000"},{"timestamp":1719187200000,"Open":"3.08600000","High":3.121,"Low":2.912,"Close":3.117,"Volume":440602.7,"quote_asset_volume":"1332234.67120000","NumTrades":15994,"taker_buy_base_asset_volume":"205848.60000000","taker_buy_quote_asset_volume":"622257.13800000"},{"timestamp":1719273600000,"Open":"3.11700000","High":3.241,"Low":3.089,"Close":3.215,"Volume":204797.5,"quote_asset_volume":"649003.93140000","NumTrades":14169,"taker_buy_base_asset_volume":"116198.70000000","taker_buy_quote_asset_volume":"368328.69060000"},{"timestamp":1719360000000,"Open":"3.21500000","High":3.261,"Low":3.128,"Close":3.158,"Volume":293896.4,"quote_asset_volume":"938614.75770000","NumTrades":16273,"taker_buy_base_asset_volume":"137602.80000000","taker_buy_quote_asset_volume":"439675.18290000"},{"timestamp":1719446400000,"Open":"3.15900000","High":3.264,"Low":3.099,"Close":3.223,"Volume":223929.2,"quote_asset_volume":"712368.20320000","NumTrades":9940,"taker_buy_base_asset_volume":"109204.70000000","taker_buy_quote_asset_volume":"347542.27670000"},{"timestamp":1719532800000,"Open":"3.22400000","High":3.432,"Low":3.17,"Close":3.206,"Volume":623319.6,"quote_asset_volume":"2049445.41170000","NumTrades":21003,"taker_buy_base_asset_volume":"307789.90000000","taker_buy_quote_asset_volume":"1014107.58160000"},{"timestamp":1719619200000,"Open":"3.20700000","High":3.3,"Low":3.105,"Close":3.108,"Volume":154084.2,"quote_asset_volume":"493689.15310000","NumTrades":9356,"taker_buy_base_asset_volume":"76209.80000000","taker_buy_quote_asset_volume":"244244.27340000"},{"timestamp":1719705600000,"Open":"3.10900000","High":3.251,"Low":3.02,"Close":3.236,"Volume":144657.9,"quote_asset_volume":"451230.47860000","NumTrades":10851,"taker_buy_base_asset_volume":"74816.60000000","taker_buy_quote_asset_volume":"233308.60970000"},{"timestamp":1719792000000,"Open":"3.23600000","High":3.317,"Low":3.156,"Close":3.161,"Volume":162816.3,"quote_asset_volume":"526667.00240000","NumTrades":9782,"taker_buy_base_asset_volume":"78107.40000000","taker_buy_quote_asset_volume":"253028.57230000"},{"timestamp":1719878400000,"Open":"3.16100000","High":3.22,"Low":3.104,"Close":3.12,"Volume":175608.2,"quote_asset_volume":"554924.42560000","NumTrades":12035,"taker_buy_base_asset_volume":"85853.40000000","taker_buy_quote_asset_volume":"271689.80350000"},{"timestamp":1719964800000,"Open":"3.12100000","High":3.291,"Low":3.05,"Close":3.078,"Volume":511398.3,"quote_asset_volume":"1600109.57010000","NumTrades":29232,"taker_buy_base_asset_volume":"285479.00000000","taker_buy_quote_asset_volume":"895332.53280000"},{"timestamp":1720051200000,"Open":"3.08100000","High":3.114,"Low":2.672,"Close":2.672,"Volume":377303.0,"quote_asset_volume":"1083199.53500000","NumTrades":18260,"taker_buy_base_asset_volume":"161179.10000000","taker_buy_quote_asset_volume":"462360.71270000"},{"timestamp":1720137600000,"Open":"2.67200000","High":3.178,"Low":2.385,"Close":2.956,"Volume":1386291.7,"quote_asset_volume":"4001725.18070000","NumTrades":63552,"taker_buy_base_asset_volume":"702050.30000000","taker_buy_quote_asset_volume":"2022668.35490000"},{"timestamp":1720224000000,"Open":"2.95700000","High":3.03,"Low":2.702,"Close":2.959,"Volume":692985.4,"quote_asset_volume":"1986525.33990000","NumTrades":31111,"taker_buy_base_asset_volume":"341485.40000000","taker_buy_quote_asset_volume":"979304.95420000"},{"timestamp":1720310400000,"Open":"2.95900000","High":3.01,"Low":2.705,"Close":2.717,"Volume":236568.7,"quote_asset_volume":"676042.62180000","NumTrades":11864,"taker_buy_base_asset_volume":"100379.00000000","taker_buy_quote_asset_volume":"286892.68490000"},{"timestamp":1720396800000,"Open":"2.72200000","High":3.236,"Low":2.617,"Close":2.856,"Volume":1095953.5,"quote_asset_volume":"3248333.09520000","NumTrades":43651,"taker_buy_base_asset_volume":"552781.20000000","taker_buy_quote_asset_volume":"1644273.30120000"},{"timestamp":1720483200000,"Open":"2.85700000","High":2.957,"Low":2.851,"Close":2.914,"Volume":258368.0,"quote_asset_volume":"749316.89610000","NumTrades":12859,"taker_buy_base_asset_volume":"130507.30000000","taker_buy_quote_asset_volume":"378653.31280000"},{"timestamp":1720569600000,"Open":"2.91500000","High":3.037,"Low":2.896,"Close":3.03,"Volume":195359.0,"quote_asset_volume":"580521.27820000","NumTrades":10136,"taker_buy_base_asset_volume":"102691.20000000","taker_buy_quote_asset_volume":"305638.87350000"},{"timestamp":1720656000000,"Open":"3.03000000","High":3.173,"Low":2.965,"Close":2.967,"Volume":442173.8,"quote_asset_volume":"1362187.87810000","NumTrades":18059,"taker_buy_base_asset_volume":"200253.70000000","taker_buy_quote_asset_volume":"618248.59330000"},{"timestamp":1720742400000,"Open":"2.97100000","High":3.056,"Low":2.898,"Close":3.055,"Volume":166178.4,"quote_asset_volume":"493574.53160000","NumTrades":8984,"taker_buy_base_asset_volume":"82783.30000000","taker_buy_quote_asset_volume":"246204.34960000"},{"timestamp":1720828800000,"Open":"3.05500000","High":3.088,"Low":3.029,"Close":3.063,"Volume":115161.2,"quote_asset_volume":"351860.70370000","NumTrades":8449,"taker_buy_base_asset_volume":"59523.00000000","taker_buy_quote_asset_volume":"181839.76850000"},{"timestamp":1720915200000,"Open":"3.06400000","High":3.2,"Low":3.053,"Close":3.192,"Volume":170660.8,"quote_asset_volume":"533081.30610000","NumTrades":13112,"taker_buy_base_asset_volume":"88603.20000000","taker_buy_quote_asset_volume":"276982.49490000"},{"timestamp":1721001600000,"Open":"3.18800000","High":3.376,"Low":3.185,"Close":3.368,"Volume":195616.7,"quote_asset_volume":"642969.83000000","NumTrades":12795,"taker_buy_base_asset_volume":"101980.60000000","taker_buy_quote_asset_volume":"335376.40640000"},{"timestamp":1721088000000,"Open":"3.36600000","High":3.384,"Low":3.2,"Close":3.36,"Volume":188094.3,"quote_asset_volume":"621500.43260000","NumTrades":14002,"taker_buy_base_asset_volume":"96298.40000000","taker_buy_quote_asset_volume":"318769.73350000"},{"timestamp":1721174400000,"Open":"3.36000000","High":3.451,"Low":3.315,"Close":3.376,"Volume":163410.1,"quote_asset_volume":"553605.16100000","NumTrades":12927,"taker_buy_base_asset_volume":"86096.30000000","taker_buy_quote_asset_volume":"291691.54920000"},{"timestamp":1721260800000,"Open":"3.37600000","High":3.536,"Low":3.195,"Close":3.238,"Volume":342107.9,"quote_asset_volume":"1158781.92710000","NumTrades":22615,"taker_buy_base_asset_volume":"156200.30000000","taker_buy_quote_asset_volume":"530765.28200000"},{"timestamp":1721347200000,"Open":"3.24200000","High":3.428,"Low":3.149,"Close":3.331,"Volume":325419.8,"quote_asset_volume":"1067227.28930000","NumTrades":20146,"taker_buy_base_asset_volume":"163146.20000000","taker_buy_quote_asset_volume":"535440.23080000"},{"timestamp":1721433600000,"Open":"3.33000000","High":3.406,"Low":3.301,"Close":3.34,"Volume":125489.3,"quote_asset_volume":"421374.88390000","NumTrades":12890,"taker_buy_base_asset_volume":"61159.30000000","taker_buy_quote_asset_volume":"205545.26840000"},{"timestamp":1721520000000,"Open":"3.33900000","High":3.416,"Low":3.223,"Close":3.365,"Volume":342559.8,"quote_asset_volume":"1144033.09930000","NumTrades":17483,"taker_buy_base_asset_volume":"172156.30000000","taker_buy_quote_asset_volume":"575497.28710000"},{"timestamp":1721606400000,"Open":"3.36500000","High":3.39,"Low":3.195,"Close":3.213,"Volume":187586.0,"quote_asset_volume":"616864.13230000","NumTrades":11329,"taker_buy_base_asset_volume":"93483.10000000","taker_buy_quote_asset_volume":"307352.11430000"},{"timestamp":1721692800000,"Open":"3.21300000","High":3.278,"Low":3.052,"Close":3.106,"Volume":187461.8,"quote_asset_volume":"594738.14630000","NumTrades":10844,"taker_buy_base_asset_volume":"87928.20000000","taker_buy_quote_asset_volume":"278687.70370000"},{"timestamp":1721779200000,"Open":"3.10600000","High":3.178,"Low":3.045,"Close":3.062,"Volume":120278.3,"quote_asset_volume":"375087.27030000","NumTrades":9292,"taker_buy_base_asset_volume":"62209.30000000","taker_buy_quote_asset_volume":"194149.36770000"},{"timestamp":1721865600000,"Open":"3.06400000","High":3.25,"Low":2.936,"Close":3.046,"Volume":522772.2,"quote_asset_volume":"1606923.09590000","NumTrades":19781,"taker_buy_base_asset_volume":"263788.70000000","taker_buy_quote_asset_volume":"814810.47850000"},{"timestamp":1721952000000,"Open":"3.04100000","High":3.189,"Low":3.04,"Close":3.166,"Volume":126853.3,"quote_asset_volume":"395470.16040000","NumTrades":8268,"taker_buy_base_asset_volume":"61906.60000000","taker_buy_quote_asset_volume":"193292.67910000"},{"timestamp":1722038400000,"Open":"3.16300000","High":3.201,"Low":3.031,"Close":3.105,"Volume":125889.6,"quote_asset_volume":"394410.33330000","NumTrades":8758,"taker_buy_base_asset_volume":"59247.30000000","taker_buy_quote_asset_volume":"185506.24760000"},{"timestamp":1722124800000,"Open":"3.10800000","High":3.276,"Low":3.06,"Close":3.108,"Volume":465372.6,"quote_asset_volume":"1476923.86350000","NumTrades":18794,"taker_buy_base_asset_volume":"239115.90000000","taker_buy_quote_asset_volume":"761456.78490000"},{"timestamp":1722211200000,"Open":"3.10800000","High":3.24,"Low":3.096,"Close":3.153,"Volume":151782.1,"quote_asset_volume":"480148.65110000","NumTrades":11145,"taker_buy_base_asset_volume":"69318.40000000","taker_buy_quote_asset_volume":"219537.82030000"},{"timestamp":1722297600000,"Open":"3.15300000","High":3.199,"Low":3.009,"Close":3.012,"Volume":193742.1,"quote_asset_volume":"602377.47090000","NumTrades":12304,"taker_buy_base_asset_volume":"94992.00000000","taker_buy_quote_asset_volume":"295326.90640000"},{"timestamp":1722384000000,"Open":"3.01500000","High":3.097,"Low":2.911,"Close":2.918,"Volume":178555.2,"quote_asset_volume":"536872.56990000","NumTrades":10468,"taker_buy_base_asset_volume":"77505.80000000","taker_buy_quote_asset_volume":"233117.39020000"},{"timestamp":1722470400000,"Open":"2.91900000","High":2.984,"Low":2.781,"Close":2.93,"Volume":287757.0,"quote_asset_volume":"835333.34520000","NumTrades":18418,"taker_buy_base_asset_volume":"145617.40000000","taker_buy_quote_asset_volume":"422947.84930000"},{"timestamp":1722556800000,"Open":"2.93000000","High":2.959,"Low":2.746,"Close":2.778,"Volume":201927.2,"quote_asset_volume":"575785.30350000","NumTrades":14412,"taker_buy_base_asset_volume":"92833.10000000","taker_buy_quote_asset_volume":"264761.94780000"},{"timestamp":1722643200000,"Open":"2.77800000","High":2.847,"Low":2.651,"Close":2.701,"Volume":215517.7,"quote_asset_volume":"592512.96980000","NumTrades":14583,"taker_buy_base_asset_volume":"109971.20000000","taker_buy_quote_asset_volume":"302424.51430000"},{"timestamp":1722729600000,"Open":"2.70200000","High":2.798,"Low":2.511,"Close":2.57,"Volume":288248.6,"quote_asset_volume":"767098.86230000","NumTrades":15051,"taker_buy_base_asset_volume":"138540.80000000","taker_buy_quote_asset_volume":"368563.91290000"},{"timestamp":1722816000000,"Open":"2.57100000","High":2.587,"Low":2.215,"Close":2.375,"Volume":759343.3,"quote_asset_volume":"1788203.90170000","NumTrades":29319,"taker_buy_base_asset_volume":"383259.30000000","taker_buy_quote_asset_volume":"901120.45380000"},{"timestamp":1722902400000,"Open":"2.37500000","High":2.552,"Low":2.368,"Close":2.507,"Volume":243503.1,"quote_asset_volume":"605686.11420000","NumTrades":15348,"taker_buy_base_asset_volume":"126565.60000000","taker_buy_quote_asset_volume":"314976.56660000"},{"timestamp":1722988800000,"Open":"2.50700000","High":2.596,"Low":2.441,"Close":2.482,"Volume":244251.2,"quote_asset_volume":"614920.29870000","NumTrades":16384,"taker_buy_base_asset_volume":"119281.90000000","taker_buy_quote_asset_volume":"300699.85010000"},{"timestamp":1723075200000,"Open":"2.48400000","High":2.776,"Low":2.451,"Close":2.773,"Volume":323113.9,"quote_asset_volume":"855032.38180000","NumTrades":18617,"taker_buy_base_asset_volume":"160145.30000000","taker_buy_quote_asset_volume":"423705.10270000"},{"timestamp":1723161600000,"Open":"2.77500000","High":2.776,"Low":2.668,"Close":2.732,"Volume":208171.0,"quote_asset_volume":"567856.90820000","NumTrades":15635,"taker_buy_base_asset_volume":"106749.50000000","taker_buy_quote_asset_volume":"291343.03730000"},{"timestamp":1723248000000,"Open":"2.73500000","High":2.753,"Low":2.672,"Close":2.673,"Volume":215061.1,"quote_asset_volume":"581759.86230000","NumTrades":18773,"taker_buy_base_asset_volume":"100624.40000000","taker_buy_quote_asset_volume":"272338.59160000"},{"timestamp":1723334400000,"Open":"2.67200000","High":2.76,"Low":2.667,"Close":2.683,"Volume":110767.2,"quote_asset_volume":"300147.67160000","NumTrades":6812,"taker_buy_base_asset_volume":"55969.10000000","taker_buy_quote_asset_volume":"151722.77990000"}]